<?xml version="1.0" encoding="UTF-8"?><a:feed xmlns:a="http://www.w3.org/2005/Atom" xmlns="http://marketplace.xboxlive.com/resource/product/v1"><a:author><a:name>Xbox LIVE</a:name></a:author><a:id>http://marketplace.xboxlive.com/resource/product/v1</a:id><a:title>Query Result</a:title><a:updated>0000-00-00 00:00:00Z</a:updated><totalItems>1</totalItems><numItems>1</numItems><locale>en-us</locale><a:entry itemNum="1" xmlns:a="http://www.w3.org/2005/Atom" xmlns="http://marketplace.xboxlive.com/resource/product/v1"><a:title>Aesir Avatar Tee</a:title><a:id>urn:uuid:00000008-6ac4-12d2-c2e3-111c5454086b</a:id><a:updated>2023-02-06T06:20:00.997Z</a:updated><a:content>game content</a:content><offerInstances><offerInstance><offerId>urn:uuid:53454000-0000-4000-8000-00005454086b</offerId><hexOfferId>0x5454086b53454000</hexOfferId><offerInstanceId>urn:uuid:9df52251-3fe6-44db-b68c-348abc19fe99</offerInstanceId><startDate>2012-01-17T09:00:00Z</startDate><endDate>2799-12-31T00:00:00Z</endDate><paymentType>2</paymentType><price>80</price><pricetext></pricetext><taxType>0</taxType><tiers><tier>2</tier></tiers><stores><store>1</store></stores><productInstance><productId>00000008-6ac4-12d2-c2e3-111c5454086b</productId><offerLicenseTypeId>12</offerLicenseTypeId><productInstanceId>b24ce557-8b73-404b-80d8-5de5984a9922</productInstanceId><isAcquirable>1</isAcquirable><isAdSupported>0</isAdSupported><packageSize>64314</packageSize><installSize>7</installSize><packageType>1</packageType><gameRegion>-1</gameRegion><contentId>skzlV4tzS9hd5ZhKmSLqg43jyNI=</contentId><licenseExtensionBits>0</licenseExtensionBits></productInstance></offerInstance><offerInstance><offerId>urn:uuid:53454000-0000-4000-8000-00005454086b</offerId><hexOfferId>0x5454086b53454000</hexOfferId><offerInstanceId>urn:uuid:7cdab220-84c7-4e61-a38b-9915eaa41c9c</offerInstanceId><startDate>2012-01-17T09:00:00Z</startDate><endDate>2799-12-31T00:00:00Z</endDate><paymentType>3</paymentType><price>1</price><pricetext>$1.00</pricetext><taxType>0</taxType><tiers><tier>2</tier></tiers><stores><store>1</store></stores><productInstance><productId>00000008-6ac4-12d2-c2e3-111c5454086b</productId><offerLicenseTypeId>12</offerLicenseTypeId><productInstanceId>b24ce557-8b73-404b-80d8-5de5984a9922</productInstanceId><isAcquirable>1</isAcquirable><isAdSupported>0</isAdSupported><packageSize>64314</packageSize><installSize>7</installSize><packageType>1</packageType><gameRegion>-1</gameRegion><contentId>skzlV4tzS9hd5ZhKmSLqg43jyNI=</contentId><licenseExtensionBits>0</licenseExtensionBits></productInstance></offerInstance><offerInstance><offerId>urn:uuid:53454000-0000-4000-8000-00005454086b</offerId><hexOfferId>0x5454086b53454000</hexOfferId><offerInstanceId>urn:uuid:fed1eaf6-1c19-494e-98db-a35e13cc2eeb</offerInstanceId><startDate>2012-01-17T09:00:00Z</startDate><endDate>2799-12-31T00:00:00Z</endDate><paymentType>1</paymentType><price>80</price><pricetext>80¤</pricetext><taxType>0</taxType><tiers><tier>2</tier></tiers><stores><store>1</store></stores><productInstance><productId>00000008-6ac4-12d2-c2e3-111c5454086b</productId><offerLicenseTypeId>12</offerLicenseTypeId><productInstanceId>b24ce557-8b73-404b-80d8-5de5984a9922</productInstanceId><isAcquirable>1</isAcquirable><isAdSupported>0</isAdSupported><packageSize>64314</packageSize><installSize>7</installSize><packageType>1</packageType><gameRegion>-1</gameRegion><contentId>skzlV4tzS9hd5ZhKmSLqg43jyNI=</contentId><licenseExtensionBits>0</licenseExtensionBits></productInstance></offerInstance><offerInstance><offerId>urn:uuid:53454000-0000-4000-8000-00005454086b</offerId><hexOfferId>0x5454086b53454000</hexOfferId><offerInstanceId>urn:uuid:fd70f669-8a0e-4e81-8645-c1b8a639b8e9</offerInstanceId><startDate>2012-01-17T09:00:00Z</startDate><endDate>2799-12-31T00:00:00Z</endDate><paymentType>1</paymentType><price>80</price><pricetext>80¤</pricetext><taxType>0</taxType><tiers><tier>3</tier></tiers><stores><store>1</store></stores><productInstance><productId>00000008-6ac4-12d2-c2e3-111c5454086b</productId><offerLicenseTypeId>12</offerLicenseTypeId><productInstanceId>b24ce557-8b73-404b-80d8-5de5984a9922</productInstanceId><isAcquirable>1</isAcquirable><isAdSupported>0</isAdSupported><packageSize>64314</packageSize><installSize>7</installSize><packageType>1</packageType><gameRegion>-1</gameRegion><contentId>skzlV4tzS9hd5ZhKmSLqg43jyNI=</contentId><licenseExtensionBits>0</licenseExtensionBits></productInstance></offerInstance><offerInstance><offerId>urn:uuid:53454000-0000-4000-8000-00005454086b</offerId><hexOfferId>0x5454086b53454000</hexOfferId><offerInstanceId>urn:uuid:1b051f03-481d-45e4-ba49-d043696a0743</offerInstanceId><startDate>2012-01-17T09:00:00Z</startDate><endDate>2799-12-31T00:00:00Z</endDate><paymentType>3</paymentType><price>1</price><pricetext>$1.00</pricetext><taxType>0</taxType><tiers><tier>3</tier></tiers><stores><store>1</store></stores><productInstance><productId>00000008-6ac4-12d2-c2e3-111c5454086b</productId><offerLicenseTypeId>12</offerLicenseTypeId><productInstanceId>b24ce557-8b73-404b-80d8-5de5984a9922</productInstanceId><isAcquirable>1</isAcquirable><isAdSupported>0</isAdSupported><packageSize>64314</packageSize><installSize>7</installSize><packageType>1</packageType><gameRegion>-1</gameRegion><contentId>skzlV4tzS9hd5ZhKmSLqg43jyNI=</contentId><licenseExtensionBits>0</licenseExtensionBits></productInstance></offerInstance><offerInstance><offerId>urn:uuid:53454000-0000-4000-8000-00005454086b</offerId><hexOfferId>0x5454086b53454000</hexOfferId><offerInstanceId>urn:uuid:0eba09fb-102d-480d-a97f-db4dda546d55</offerInstanceId><startDate>2012-01-17T09:00:00Z</startDate><endDate>2799-12-31T00:00:00Z</endDate><paymentType>2</paymentType><price>80</price><pricetext></pricetext><taxType>0</taxType><tiers><tier>3</tier></tiers><stores><store>1</store></stores><productInstance><productId>00000008-6ac4-12d2-c2e3-111c5454086b</productId><offerLicenseTypeId>12</offerLicenseTypeId><productInstanceId>b24ce557-8b73-404b-80d8-5de5984a9922</productInstanceId><isAcquirable>1</isAcquirable><isAdSupported>0</isAdSupported><packageSize>64314</packageSize><installSize>7</installSize><packageType>1</packageType><gameRegion>-1</gameRegion><contentId>skzlV4tzS9hd5ZhKmSLqg43jyNI=</contentId><licenseExtensionBits>0</licenseExtensionBits></productInstance></offerInstance></offerInstances><productType>47</productType><reducedTitle>Aesir Avatar Tee</reducedTitle><reducedDescription>Get “a bit closer to heaven” in the Aesir logo tee</reducedDescription><fullTitle>Aesir Avatar Tee</fullTitle><fullDescription>Get “a bit closer to heaven” in the Aesir logo tee</fullDescription><visibilityDate>2011-10-31T00:00:00</visibilityDate><globalOriginalReleaseDate>2012-01-17T00:00:00</globalOriginalReleaseDate><developerName>Rockstar Studios</developerName><publisherName>Rockstar Games</publisherName><titleId>1414793323</titleId><hexTitleId>0x5454086b</hexTitleId><effectiveTitleId>1414793323</effectiveTitleId><gameReducedTitle>Max Payne 3</gameReducedTitle><avatarBodyType>2</avatarBodyType><avatarItemAssetId>00000008-6AC4-12D2-C2E3-111C5454086B</avatarItemAssetId><userRating>0.00</userRating><numberOfRatings>0</numberOfRatings><images><image><imageMediaId>1223A211-1EF7-4F56-9272-6561205EF84C</imageMediaId><imageMediaInstanceId>F9AA5A88-D59B-4A4C-95AE-158B2DE7C373</imageMediaInstanceId><imageMediaType>14</imageMediaType><relationshipType>33</relationshipType><format>4</format><size>30</size><fileUrl>http://download.xbox.com/content/images/66acd000-77fe-1000-9115-d8025454086b/1033/boxartsm.jpg</fileUrl><parentGameMediaId>66ACD000-77FE-1000-9115-D8025454086B</parentGameMediaId></image><image><imageMediaId>B3384A59-84F3-48C7-A06D-5CF274A41CAA</imageMediaId><imageMediaInstanceId>8AA36D10-2EF0-4A4C-A7DB-7634ADF9E163</imageMediaInstanceId><imageMediaType>14</imageMediaType><relationshipType>33</relationshipType><format>4</format><size>23</size><fileUrl>http://download.xbox.com/content/images/66acd000-77fe-1000-9115-d8025454086b/1033/boxartlg.jpg</fileUrl><parentGameMediaId>66ACD000-77FE-1000-9115-D8025454086B</parentGameMediaId></image><image><imageMediaId>B3863FFE-2B29-4F13-8999-C95EF73B6D54</imageMediaId><imageMediaInstanceId>2F32C772-B4C1-4DC5-B5A1-09C28CD53529</imageMediaInstanceId><imageMediaType>14</imageMediaType><relationshipType>15</relationshipType><format>5</format><size>32</size><fileUrl>http://download.xbox.com/content/images/00000008-6ac4-12d2-c2e3-111c5454086b/0/thumbm.png</fileUrl><parentGameMediaId>00000008-6AC4-12D2-C2E3-111C5454086B</parentGameMediaId></image><image><imageMediaId>1AB18BEB-1408-43C0-90A9-E155D77051A9</imageMediaId><imageMediaInstanceId>21A22441-A4A1-4847-91C9-25578D8D40C2</imageMediaInstanceId><imageMediaType>14</imageMediaType><relationshipType>33</relationshipType><format>4</format><size>23</size><fileUrl>http://download.xbox.com/content/images/66acd000-77fe-1000-9115-d802584d07d1/1033/boxartlg.jpg</fileUrl><parentGameMediaId>66ACD000-77FE-1000-9115-D802584D07D1</parentGameMediaId></image><image><imageMediaId>2BEFB2B3-B431-4EA3-B6E4-CE01D7BBB268</imageMediaId><imageMediaInstanceId>31F7171E-DAD0-4992-9653-4DD15EC26FB1</imageMediaInstanceId><imageMediaType>14</imageMediaType><relationshipType>15</relationshipType><format>5</format><size>14</size><fileUrl>http://download.xbox.com/content/images/00000008-6ac4-12d2-c2e3-111c5454086b/0/thumbsm.png</fileUrl><parentGameMediaId>00000008-6AC4-12D2-C2E3-111C5454086B</parentGameMediaId></image><image><imageMediaId>35821D06-0B7C-444A-BF1C-BA17EE65770C</imageMediaId><imageMediaInstanceId>CBA2A729-71D3-4A10-A5B7-91072AF296A8</imageMediaInstanceId><imageMediaType>14</imageMediaType><relationshipType>33</relationshipType><format>4</format><size>30</size><fileUrl>http://download.xbox.com/content/images/66acd000-77fe-1000-9115-d802584d07d1/1033/boxartsm.jpg</fileUrl><parentGameMediaId>66ACD000-77FE-1000-9115-D802584D07D1</parentGameMediaId></image><image><imageMediaId>80CF753F-ED3F-4BCC-90CC-F9AE05C3F28E</imageMediaId><imageMediaInstanceId>5EC968B9-ED9B-460B-8319-BEC3C37A3CE0</imageMediaInstanceId><imageMediaType>14</imageMediaType><relationshipType>15</relationshipType><format>5</format><size>25</size><fileUrl>http://download.xbox.com/content/images/00000008-6ac4-12d2-c2e3-111c5454086b/0/thumblg.png</fileUrl><parentGameMediaId>00000008-6AC4-12D2-C2E3-111C5454086B</parentGameMediaId></image><image><imageMediaId>86B891A2-5798-418B-940A-A5332E3F5C7D</imageMediaId><imageMediaInstanceId>8DD8FB3B-4896-466D-BB15-D8996EE9AA30</imageMediaInstanceId><imageMediaType>14</imageMediaType><relationshipType>27</relationshipType><format>5</format><size>15</size><fileUrl>http://download.xbox.com/content/images/00000008-6ac4-12d2-c2e3-111c5454086b/1033/banner.png</fileUrl><parentGameMediaId>00000008-6AC4-12D2-C2E3-111C5454086B</parentGameMediaId></image></images><parentProducts><parentProduct><parentProductId>66acd000-77fe-1000-9115-d8025454086b</parentProductId><parentReducedTitle>Max Payne 3</parentReducedTitle><parentSortOrder>0</parentSortOrder></parentProduct></parentProducts><categories><category><categoryId>3000</categoryId><categoryName>Game Genres</categoryName><categorySystemId>3000</categorySystemId></category><category><categoryId>3002</categoryId><categoryName>Action &amp; Adventure</categoryName><categorySystemId>3000</categorySystemId><parentCategoryId>3027</parentCategoryId></category><category><categoryId>3025</categoryId><categoryName>Xbox LIVE Marketplace</categoryName><categorySystemId>3000</categorySystemId><parentCategoryId>3000</parentCategoryId></category><category><categoryId>3027</categoryId><categoryName>Xbox LIVE Games</categoryName><categorySystemId>3000</categorySystemId><parentCategoryId>3000</parentCategoryId></category><category><categoryId>3312</categoryId><categoryName>Independent &amp; Music Videos</categoryName><categorySystemId>3000</categorySystemId><parentCategoryId>3025</parentCategoryId></category><category><categoryId>3314</categoryId><categoryName>Music and Short Videos</categoryName><categorySystemId>3000</categorySystemId><parentCategoryId>3312</parentCategoryId></category><category><categoryId>3317</categoryId><categoryName>Xbox 360 Exclusives</categoryName><categorySystemId>3000</categorySystemId><parentCategoryId>3314</parentCategoryId></category><category><categoryId>12001</categoryId><categoryName>Game Publisher Bit 1</categoryName><categorySystemId>12000</categorySystemId></category><category><categoryId>13001</categoryId><categoryName>All Items</categoryName><categorySystemId>13000</categorySystemId></category><category><categoryId>13200</categoryId><categoryName>Tops</categoryName><categorySystemId>13000</categorySystemId><parentCategoryId>13001</parentCategoryId></category><category><categoryId>13201</categoryId><categoryName>Sport Tee</categoryName><categorySystemId>13000</categorySystemId><parentCategoryId>13200</parentCategoryId></category></categories><showRating>false</showRating></a:entry></a:feed>