<?xml version="1.0" encoding="UTF-8"?><a:feed xmlns:a="http://www.w3.org/2005/Atom" xmlns="http://marketplace.xboxlive.com/resource/product/v1"><a:author><a:name>Xbox LIVE</a:name></a:author><a:id>http://marketplace.xboxlive.com/resource/product/v1</a:id><a:title>Query Result</a:title><a:updated>0000-00-00 00:00:00Z</a:updated><totalItems>1</totalItems><numItems>1</numItems><locale>en-us</locale><a:entry itemNum="1" xmlns:a="http://www.w3.org/2005/Atom" xmlns="http://marketplace.xboxlive.com/resource/product/v1"><a:title>T-Shirt - RoboCop Face</a:title><a:id>urn:uuid:00000008-2799-9261-c81d-f0105858087d</a:id><a:updated>2015-10-20T00:35:32.750Z</a:updated><a:content>game content</a:content><offerInstances><offerInstance><offerId>urn:uuid:02848000-0000-4000-8000-00005858087d</offerId><hexOfferId>0x5858087d02848000</hexOfferId><offerInstanceId>urn:uuid:7e65e6ea-9bed-4400-8621-189966c20b84</offerInstanceId><startDate>2011-08-30T09:00:00Z</startDate><endDate>2015-10-19T00:00:00Z</endDate><paymentType>3</paymentType><price>1</price><pricetext>$1.00</pricetext><taxType>0</taxType><tiers><tier>3</tier></tiers><stores><store>1</store></stores><productInstance><productId>00000008-2799-9261-c81d-f0105858087d</productId><offerLicenseTypeId>12</offerLicenseTypeId><productInstanceId>2f402577-e3bd-40a2-80cc-30d6ad502f85</productInstanceId><isAcquirable>1</isAcquirable><isAdSupported>0</isAdSupported><packageSize>56757</packageSize><installSize>6</installSize><packageType>1</packageType><gameRegion>-1</gameRegion><contentId>L0Ald+O9osww1q1QL4UND/wHjUg=</contentId><licenseExtensionBits>0</licenseExtensionBits></productInstance></offerInstance><offerInstance><offerId>urn:uuid:02848000-0000-4000-8000-00005858087d</offerId><hexOfferId>0x5858087d02848000</hexOfferId><offerInstanceId>urn:uuid:525e29b5-227b-4f48-9bf7-3e2e29925862</offerInstanceId><startDate>2011-08-30T09:00:00Z</startDate><endDate>2015-10-19T00:00:00Z</endDate><paymentType>1</paymentType><price>80</price><pricetext>80¤</pricetext><taxType>0</taxType><tiers><tier>2</tier></tiers><stores><store>1</store></stores><productInstance><productId>00000008-2799-9261-c81d-f0105858087d</productId><offerLicenseTypeId>12</offerLicenseTypeId><productInstanceId>2f402577-e3bd-40a2-80cc-30d6ad502f85</productInstanceId><isAcquirable>1</isAcquirable><isAdSupported>0</isAdSupported><packageSize>56757</packageSize><installSize>6</installSize><packageType>1</packageType><gameRegion>-1</gameRegion><contentId>L0Ald+O9osww1q1QL4UND/wHjUg=</contentId><licenseExtensionBits>0</licenseExtensionBits></productInstance></offerInstance><offerInstance><offerId>urn:uuid:02848000-0000-4000-8000-00005858087d</offerId><hexOfferId>0x5858087d02848000</hexOfferId><offerInstanceId>urn:uuid:e688cd27-54c2-43a7-8418-8987335de3c2</offerInstanceId><startDate>2011-08-30T09:00:00Z</startDate><endDate>2015-10-19T00:00:00Z</endDate><paymentType>1</paymentType><price>80</price><pricetext>80¤</pricetext><taxType>0</taxType><tiers><tier>3</tier></tiers><stores><store>1</store></stores><productInstance><productId>00000008-2799-9261-c81d-f0105858087d</productId><offerLicenseTypeId>12</offerLicenseTypeId><productInstanceId>2f402577-e3bd-40a2-80cc-30d6ad502f85</productInstanceId><isAcquirable>1</isAcquirable><isAdSupported>0</isAdSupported><packageSize>56757</packageSize><installSize>6</installSize><packageType>1</packageType><gameRegion>-1</gameRegion><contentId>L0Ald+O9osww1q1QL4UND/wHjUg=</contentId><licenseExtensionBits>0</licenseExtensionBits></productInstance></offerInstance><offerInstance><offerId>urn:uuid:02848000-0000-4000-8000-00005858087d</offerId><hexOfferId>0x5858087d02848000</hexOfferId><offerInstanceId>urn:uuid:eba68a81-108f-4cf3-b1df-9ce415cb9285</offerInstanceId><startDate>2013-04-26T00:00:00Z</startDate><endDate>2799-12-31T00:00:00Z</endDate><paymentType>2</paymentType><price>80</price><pricetext></pricetext><taxType>0</taxType><tiers><tier>2</tier></tiers><stores><store>1</store></stores><productInstance><productId>00000008-2799-9261-c81d-f0105858087d</productId><offerLicenseTypeId>12</offerLicenseTypeId><productInstanceId>2f402577-e3bd-40a2-80cc-30d6ad502f85</productInstanceId><isAcquirable>1</isAcquirable><isAdSupported>0</isAdSupported><packageSize>56757</packageSize><installSize>6</installSize><packageType>1</packageType><gameRegion>-1</gameRegion><contentId>L0Ald+O9osww1q1QL4UND/wHjUg=</contentId><licenseExtensionBits>0</licenseExtensionBits></productInstance></offerInstance><offerInstance><offerId>urn:uuid:02848000-0000-4000-8000-00005858087d</offerId><hexOfferId>0x5858087d02848000</hexOfferId><offerInstanceId>urn:uuid:384011b2-9a99-41fd-87ae-a22462ea1433</offerInstanceId><startDate>2011-08-30T09:00:00Z</startDate><endDate>2015-10-19T00:00:00Z</endDate><paymentType>3</paymentType><price>1</price><pricetext>$1.00</pricetext><taxType>0</taxType><tiers><tier>2</tier></tiers><stores><store>1</store></stores><productInstance><productId>00000008-2799-9261-c81d-f0105858087d</productId><offerLicenseTypeId>12</offerLicenseTypeId><productInstanceId>2f402577-e3bd-40a2-80cc-30d6ad502f85</productInstanceId><isAcquirable>1</isAcquirable><isAdSupported>0</isAdSupported><packageSize>56757</packageSize><installSize>6</installSize><packageType>1</packageType><gameRegion>-1</gameRegion><contentId>L0Ald+O9osww1q1QL4UND/wHjUg=</contentId><licenseExtensionBits>0</licenseExtensionBits></productInstance></offerInstance><offerInstance><offerId>urn:uuid:02848000-0000-4000-8000-00005858087d</offerId><hexOfferId>0x5858087d02848000</hexOfferId><offerInstanceId>urn:uuid:65cd2da7-22d4-4195-a6f0-c7dd14fd2898</offerInstanceId><startDate>2013-04-26T00:00:00Z</startDate><endDate>2799-12-31T00:00:00Z</endDate><paymentType>2</paymentType><price>80</price><pricetext></pricetext><taxType>0</taxType><tiers><tier>3</tier></tiers><stores><store>1</store></stores><productInstance><productId>00000008-2799-9261-c81d-f0105858087d</productId><offerLicenseTypeId>12</offerLicenseTypeId><productInstanceId>2f402577-e3bd-40a2-80cc-30d6ad502f85</productInstanceId><isAcquirable>1</isAcquirable><isAdSupported>0</isAdSupported><packageSize>56757</packageSize><installSize>6</installSize><packageType>1</packageType><gameRegion>-1</gameRegion><contentId>L0Ald+O9osww1q1QL4UND/wHjUg=</contentId><licenseExtensionBits>0</licenseExtensionBits></productInstance></offerInstance></offerInstances><productType>47</productType><reducedTitle>T-Shirt - RoboCop Face</reducedTitle><reducedDescription>T-Shirt: RoboCop's pretty mug. On a shirt. </reducedDescription><fullTitle>T-Shirt - RoboCop Face </fullTitle><fullDescription>T-Shirt: RoboCop's pretty mug. On a shirt. </fullDescription><visibilityDate>2011-08-25T00:00:00</visibilityDate><globalOriginalReleaseDate>2011-08-25T00:00:00</globalOriginalReleaseDate><developerName>Xbox LIVE</developerName><publisherName>Xbox  LIVE</publisherName><titleId>1482164349</titleId><hexTitleId>0x5858087d</hexTitleId><effectiveTitleId>1482164349</effectiveTitleId><gameReducedTitle>RoboCop</gameReducedTitle><avatarBodyType>1</avatarBodyType><avatarItemAssetId>00000008-2799-9261-C81D-F0105858087D</avatarItemAssetId><images><image><imageMediaId>D2489DED-5925-4268-B046-C7406049C1AF</imageMediaId><imageMediaInstanceId>7F65C7EE-C3A4-435F-A3CB-7E7AD86B3D83</imageMediaInstanceId><imageMediaType>14</imageMediaType><relationshipType>33</relationshipType><format>4</format><size>23</size><fileUrl>http://download.xbox.com/content/images/66acd000-77fe-1000-9115-d8025858087d/1033/boxartlg.jpg</fileUrl><parentGameMediaId>66ACD000-77FE-1000-9115-D8025858087D</parentGameMediaId></image><image><imageMediaId>1AA91178-15CE-4221-8918-EDAA5E79E716</imageMediaId><imageMediaInstanceId>010507B3-1FF7-4F92-A02C-B4F461BBEC8A</imageMediaInstanceId><imageMediaType>14</imageMediaType><relationshipType>33</relationshipType><format>4</format><size>30</size><fileUrl>http://download.xbox.com/content/images/66acd000-77fe-1000-9115-d8025858087d/1033/boxartsm.jpg</fileUrl><parentGameMediaId>66ACD000-77FE-1000-9115-D8025858087D</parentGameMediaId></image><image><imageMediaId>471144BB-88B7-482A-B311-0FBA71FF190E</imageMediaId><imageMediaInstanceId>7A2BC133-CD5D-48BE-AF0E-23555934C8A6</imageMediaInstanceId><imageMediaType>14</imageMediaType><relationshipType>15</relationshipType><format>5</format><size>14</size><fileUrl>http://download.xbox.com/content/images/00000008-2799-9261-c81d-f0105858087d/1033/thumbsm.png</fileUrl><parentGameMediaId>00000008-2799-9261-C81D-F0105858087D</parentGameMediaId></image><image><imageMediaId>1AB18BEB-1408-43C0-90A9-E155D77051A9</imageMediaId><imageMediaInstanceId>21A22441-A4A1-4847-91C9-25578D8D40C2</imageMediaInstanceId><imageMediaType>14</imageMediaType><relationshipType>33</relationshipType><format>4</format><size>23</size><fileUrl>http://download.xbox.com/content/images/66acd000-77fe-1000-9115-d802584d07d1/1033/boxartlg.jpg</fileUrl><parentGameMediaId>66ACD000-77FE-1000-9115-D802584D07D1</parentGameMediaId></image><image><imageMediaId>8C22743F-843A-40CF-B324-E780E4F318EC</imageMediaId><imageMediaInstanceId>2FC8FB48-59AE-4383-80EE-36111473EB99</imageMediaInstanceId><imageMediaType>14</imageMediaType><relationshipType>15</relationshipType><format>5</format><size>25</size><fileUrl>http://download.xbox.com/content/images/00000008-2799-9261-c81d-f0105858087d/1033/thumblg.png</fileUrl><parentGameMediaId>00000008-2799-9261-C81D-F0105858087D</parentGameMediaId></image><image><imageMediaId>35821D06-0B7C-444A-BF1C-BA17EE65770C</imageMediaId><imageMediaInstanceId>CBA2A729-71D3-4A10-A5B7-91072AF296A8</imageMediaInstanceId><imageMediaType>14</imageMediaType><relationshipType>33</relationshipType><format>4</format><size>30</size><fileUrl>http://download.xbox.com/content/images/66acd000-77fe-1000-9115-d802584d07d1/1033/boxartsm.jpg</fileUrl><parentGameMediaId>66ACD000-77FE-1000-9115-D802584D07D1</parentGameMediaId></image><image><imageMediaId>D90407A4-594E-4C8C-8AB4-13592150FA76</imageMediaId><imageMediaInstanceId>FF8D39E7-5C0E-457D-A215-C73C11629C91</imageMediaInstanceId><imageMediaType>14</imageMediaType><relationshipType>27</relationshipType><format>5</format><size>15</size><fileUrl>http://download.xbox.com/content/images/00000008-2799-9261-c81d-f0105858087d/1033/banner.png</fileUrl><parentGameMediaId>00000008-2799-9261-C81D-F0105858087D</parentGameMediaId></image><image><imageMediaId>79427915-170B-4453-83DE-488E52F56844</imageMediaId><imageMediaInstanceId>3F6EFA87-2C62-4C0F-B76D-F765D338360C</imageMediaInstanceId><imageMediaType>14</imageMediaType><relationshipType>15</relationshipType><format>5</format><size>32</size><fileUrl>http://download.xbox.com/content/images/00000008-2799-9261-c81d-f0105858087d/1033/thumbm.png</fileUrl><parentGameMediaId>00000008-2799-9261-C81D-F0105858087D</parentGameMediaId></image></images><categories><category><categoryId>3000</categoryId><categoryName>Game Genres</categoryName><categorySystemId>3000</categorySystemId></category><category><categoryId>3025</categoryId><categoryName>Xbox LIVE Marketplace</categoryName><categorySystemId>3000</categorySystemId><parentCategoryId>3000</parentCategoryId></category><category><categoryId>3312</categoryId><categoryName>Independent &amp; Music Videos</categoryName><categorySystemId>3000</categorySystemId><parentCategoryId>3025</parentCategoryId></category><category><categoryId>3314</categoryId><categoryName>Music and Short Videos</categoryName><categorySystemId>3000</categorySystemId><parentCategoryId>3312</parentCategoryId></category><category><categoryId>3317</categoryId><categoryName>Xbox 360 Exclusives</categoryName><categorySystemId>3000</categorySystemId><parentCategoryId>3314</parentCategoryId></category><category><categoryId>12001</categoryId><categoryName>Game Publisher Bit 1</categoryName><categorySystemId>12000</categorySystemId></category><category><categoryId>13001</categoryId><categoryName>All Items</categoryName><categorySystemId>13000</categorySystemId></category><category><categoryId>13200</categoryId><categoryName>Tops</categoryName><categorySystemId>13000</categorySystemId><parentCategoryId>13001</parentCategoryId></category><category><categoryId>13202</categoryId><categoryName>Tee</categoryName><categorySystemId>13000</categorySystemId><parentCategoryId>13200</parentCategoryId></category><category><categoryId>14001</categoryId><categoryName>Life Style</categoryName><categorySystemId>14000</categorySystemId></category><category><categoryId>14282</categoryId><categoryName>RoboCop</categoryName><categorySystemId>14000</categorySystemId><parentCategoryId>14001</parentCategoryId></category></categories><showRating>false</showRating></a:entry></a:feed>