<?xml version="1.0" encoding="UTF-8"?><a:feed xmlns:a="http://www.w3.org/2005/Atom" xmlns="http://marketplace.xboxlive.com/resource/product/v1"><a:author><a:name>Xbox LIVE</a:name></a:author><a:id>http://marketplace.xboxlive.com/resource/product/v1</a:id><a:title>Query Result</a:title><a:updated>0000-00-00 00:00:00Z</a:updated><totalItems>1</totalItems><numItems>1</numItems><locale>en-us</locale><a:entry itemNum="1" xmlns:a="http://www.w3.org/2005/Atom" xmlns="http://marketplace.xboxlive.com/resource/product/v1"><a:title>Siberian Tiger</a:title><a:id>urn:uuid:00001000-50e1-b203-c659-b93f4d530a95</a:id><a:updated>2023-02-07T10:20:04.270Z</a:updated><a:content>game content</a:content><offerInstances><offerInstance><offerId>urn:uuid:cbfd9800-0000-4000-8000-00004d530a95</offerId><hexOfferId>0x4d530a95cbfd9800</hexOfferId><offerInstanceId>urn:uuid:97691153-f2f8-41ff-b735-15ba02606cde</offerInstanceId><startDate>2014-01-01T09:00:00Z</startDate><endDate>2799-12-31T00:00:00Z</endDate><paymentType>3</paymentType><price>2.99</price><pricetext>$2.99</pricetext><taxType>0</taxType><tiers><tier>2</tier></tiers><stores><store>1</store></stores><productInstance><productId>00001000-50e1-b203-c659-b93f4d530a95</productId><offerLicenseTypeId>12</offerLicenseTypeId><productInstanceId>6234910f-04b1-40f4-8087-8e14402db9e1</productInstanceId><isAcquirable>1</isAcquirable><isAdSupported>0</isAdSupported><packageSize>219860</packageSize><installSize>18</installSize><packageType>1</packageType><gameRegion>-1</gameRegion><contentId>YjSRDwSx9IeOFEAtueFITPL31cQ=</contentId><licenseExtensionBits>0</licenseExtensionBits></productInstance></offerInstance><offerInstance><offerId>urn:uuid:cbfd9800-0000-4000-8000-00004d530a95</offerId><hexOfferId>0x4d530a95cbfd9800</hexOfferId><offerInstanceId>urn:uuid:0731cfa4-6ecb-4838-9429-3adb24864a9c</offerInstanceId><startDate>2013-10-09T09:00:00Z</startDate><endDate>2799-12-31T00:00:00Z</endDate><paymentType>2</paymentType><price>240</price><pricetext></pricetext><taxType>0</taxType><tiers><tier>3</tier></tiers><stores><store>1</store></stores><productInstance><productId>00001000-50e1-b203-c659-b93f4d530a95</productId><offerLicenseTypeId>12</offerLicenseTypeId><productInstanceId>6234910f-04b1-40f4-8087-8e14402db9e1</productInstanceId><isAcquirable>1</isAcquirable><isAdSupported>0</isAdSupported><packageSize>219860</packageSize><installSize>18</installSize><packageType>1</packageType><gameRegion>-1</gameRegion><contentId>YjSRDwSx9IeOFEAtueFITPL31cQ=</contentId><licenseExtensionBits>0</licenseExtensionBits></productInstance></offerInstance><offerInstance><offerId>urn:uuid:cbfd9800-0000-4000-8000-00004d530a95</offerId><hexOfferId>0x4d530a95cbfd9800</hexOfferId><offerInstanceId>urn:uuid:ae708bfd-0f6e-4c64-8550-46a3aa53e2f9</offerInstanceId><startDate>2013-10-09T09:00:00Z</startDate><endDate>2799-12-31T00:00:00Z</endDate><paymentType>2</paymentType><price>240</price><pricetext></pricetext><taxType>0</taxType><tiers><tier>2</tier></tiers><stores><store>1</store></stores><productInstance><productId>00001000-50e1-b203-c659-b93f4d530a95</productId><offerLicenseTypeId>12</offerLicenseTypeId><productInstanceId>6234910f-04b1-40f4-8087-8e14402db9e1</productInstanceId><isAcquirable>1</isAcquirable><isAdSupported>0</isAdSupported><packageSize>219860</packageSize><installSize>18</installSize><packageType>1</packageType><gameRegion>-1</gameRegion><contentId>YjSRDwSx9IeOFEAtueFITPL31cQ=</contentId><licenseExtensionBits>0</licenseExtensionBits></productInstance></offerInstance><offerInstance><offerId>urn:uuid:cbfd9800-0000-4000-8000-00004d530a95</offerId><hexOfferId>0x4d530a95cbfd9800</hexOfferId><offerInstanceId>urn:uuid:0353ea89-b643-4608-b84b-98e28dbf199e</offerInstanceId><startDate>2014-01-01T09:00:00Z</startDate><endDate>2799-12-31T00:00:00Z</endDate><paymentType>1</paymentType><price>240</price><pricetext>240¤</pricetext><taxType>0</taxType><tiers><tier>2</tier></tiers><stores><store>1</store></stores><productInstance><productId>00001000-50e1-b203-c659-b93f4d530a95</productId><offerLicenseTypeId>12</offerLicenseTypeId><productInstanceId>6234910f-04b1-40f4-8087-8e14402db9e1</productInstanceId><isAcquirable>1</isAcquirable><isAdSupported>0</isAdSupported><packageSize>219860</packageSize><installSize>18</installSize><packageType>1</packageType><gameRegion>-1</gameRegion><contentId>YjSRDwSx9IeOFEAtueFITPL31cQ=</contentId><licenseExtensionBits>0</licenseExtensionBits></productInstance></offerInstance><offerInstance><offerId>urn:uuid:cbfd9800-0000-4000-8000-00004d530a95</offerId><hexOfferId>0x4d530a95cbfd9800</hexOfferId><offerInstanceId>urn:uuid:6f62de74-2fbc-4df2-a121-bf7485d323a6</offerInstanceId><startDate>2014-01-01T09:00:00Z</startDate><endDate>2799-12-31T00:00:00Z</endDate><paymentType>3</paymentType><price>2.99</price><pricetext>$2.99</pricetext><taxType>0</taxType><tiers><tier>3</tier></tiers><stores><store>1</store></stores><productInstance><productId>00001000-50e1-b203-c659-b93f4d530a95</productId><offerLicenseTypeId>12</offerLicenseTypeId><productInstanceId>6234910f-04b1-40f4-8087-8e14402db9e1</productInstanceId><isAcquirable>1</isAcquirable><isAdSupported>0</isAdSupported><packageSize>219860</packageSize><installSize>18</installSize><packageType>1</packageType><gameRegion>-1</gameRegion><contentId>YjSRDwSx9IeOFEAtueFITPL31cQ=</contentId><licenseExtensionBits>0</licenseExtensionBits></productInstance></offerInstance><offerInstance><offerId>urn:uuid:cbfd9800-0000-4000-8000-00004d530a95</offerId><hexOfferId>0x4d530a95cbfd9800</hexOfferId><offerInstanceId>urn:uuid:5272c9c8-a510-43d7-8fd3-e464ca6dd385</offerInstanceId><startDate>2014-01-01T09:00:00Z</startDate><endDate>2799-12-31T00:00:00Z</endDate><paymentType>1</paymentType><price>240</price><pricetext>240¤</pricetext><taxType>0</taxType><tiers><tier>3</tier></tiers><stores><store>1</store></stores><productInstance><productId>00001000-50e1-b203-c659-b93f4d530a95</productId><offerLicenseTypeId>12</offerLicenseTypeId><productInstanceId>6234910f-04b1-40f4-8087-8e14402db9e1</productInstanceId><isAcquirable>1</isAcquirable><isAdSupported>0</isAdSupported><packageSize>219860</packageSize><installSize>18</installSize><packageType>1</packageType><gameRegion>-1</gameRegion><contentId>YjSRDwSx9IeOFEAtueFITPL31cQ=</contentId><licenseExtensionBits>0</licenseExtensionBits></productInstance></offerInstance></offerInstances><productType>47</productType><reducedTitle>Siberian Tiger</reducedTitle><reducedDescription>Download this avatar item.</reducedDescription><fullTitle>Zoo Tycoon Siberian Tiger</fullTitle><fullDescription>Download this avatar item.</fullDescription><voiceDisplayTitle>Zoo Tycoon Siberian Tiger</voiceDisplayTitle><visibilityDate>2010-11-01T00:00:00</visibilityDate><globalOriginalReleaseDate>2014-01-01T00:00:00</globalOriginalReleaseDate><developerName>Frontier Developments plc</developerName><publisherName>Microsoft Studios</publisherName><titleId>1297287829</titleId><hexTitleId>0x4d530a95</hexTitleId><effectiveTitleId>1297287829</effectiveTitleId><gameReducedTitle>Zoo Tycoon</gameReducedTitle><avatarBodyType>3</avatarBodyType><avatarItemAssetId>00001000-50E1-B203-C659-B93F4D530A95</avatarItemAssetId><userRating>4.00</userRating><numberOfRatings>22</numberOfRatings><images><image><imageMediaId>28DFBAEF-8F28-4F31-B55E-9B714DAFB281</imageMediaId><imageMediaInstanceId>6E4208BE-191A-46A3-9FD8-56F688F98B5F</imageMediaInstanceId><imageMediaType>14</imageMediaType><relationshipType>33</relationshipType><format>4</format><size>30</size><fileUrl>http://download.xbox.com/content/images/66acd000-77fe-1000-9115-d8024d530a95/1033/boxartsm.jpg</fileUrl><parentGameMediaId>66ACD000-77FE-1000-9115-D8024D530A95</parentGameMediaId></image><image><imageMediaId>BDA8A33D-27A8-40A0-B06A-CFDD44D9A784</imageMediaId><imageMediaInstanceId>ECA27C19-2BD3-433E-A15F-85951260B041</imageMediaInstanceId><imageMediaType>14</imageMediaType><relationshipType>33</relationshipType><format>4</format><size>23</size><fileUrl>http://download.xbox.com/content/images/66acd000-77fe-1000-9115-d8024d530a95/1033/boxartlg.jpg</fileUrl><parentGameMediaId>66ACD000-77FE-1000-9115-D8024D530A95</parentGameMediaId></image><image><imageMediaId>1AB18BEB-1408-43C0-90A9-E155D77051A9</imageMediaId><imageMediaInstanceId>21A22441-A4A1-4847-91C9-25578D8D40C2</imageMediaInstanceId><imageMediaType>14</imageMediaType><relationshipType>33</relationshipType><format>4</format><size>23</size><fileUrl>http://download.xbox.com/content/images/66acd000-77fe-1000-9115-d802584d07d1/1033/boxartlg.jpg</fileUrl><parentGameMediaId>66ACD000-77FE-1000-9115-D802584D07D1</parentGameMediaId></image><image><imageMediaId>B8E4C7EF-180B-4C53-B14F-8F87D30364E8</imageMediaId><imageMediaInstanceId>ADA97939-9786-4E24-B154-35F1A576D8C7</imageMediaInstanceId><imageMediaType>14</imageMediaType><relationshipType>15</relationshipType><format>5</format><size>14</size><fileUrl>http://download.xbox.com/content/images/00001000-50e1-b203-c659-b93f4d530a95/1033/thumbsm.png</fileUrl><parentGameMediaId>00001000-50E1-B203-C659-B93F4D530A95</parentGameMediaId></image><image><imageMediaId>D2E602B0-4294-4AE2-A556-34930D452823</imageMediaId><imageMediaInstanceId>C9767635-EC66-406C-BFE6-53EEB593618F</imageMediaInstanceId><imageMediaType>14</imageMediaType><relationshipType>27</relationshipType><format>5</format><size>15</size><fileUrl>http://download.xbox.com/content/images/00001000-50e1-b203-c659-b93f4d530a95/1033/banner.png</fileUrl><parentGameMediaId>00001000-50E1-B203-C659-B93F4D530A95</parentGameMediaId></image><image><imageMediaId>35821D06-0B7C-444A-BF1C-BA17EE65770C</imageMediaId><imageMediaInstanceId>CBA2A729-71D3-4A10-A5B7-91072AF296A8</imageMediaInstanceId><imageMediaType>14</imageMediaType><relationshipType>33</relationshipType><format>4</format><size>30</size><fileUrl>http://download.xbox.com/content/images/66acd000-77fe-1000-9115-d802584d07d1/1033/boxartsm.jpg</fileUrl><parentGameMediaId>66ACD000-77FE-1000-9115-D802584D07D1</parentGameMediaId></image><image><imageMediaId>EB289245-8FDE-4EC2-811C-BB735B360314</imageMediaId><imageMediaInstanceId>0A3E6847-22BD-4523-850D-A053B9C1E68D</imageMediaInstanceId><imageMediaType>14</imageMediaType><relationshipType>15</relationshipType><format>5</format><size>25</size><fileUrl>http://download.xbox.com/content/images/00001000-50e1-b203-c659-b93f4d530a95/1033/thumblg.png</fileUrl><parentGameMediaId>00001000-50E1-B203-C659-B93F4D530A95</parentGameMediaId></image><image><imageMediaId>26B00BB2-222A-4B55-BFC5-A4D646A59BBF</imageMediaId><imageMediaInstanceId>17C4705C-3F83-4977-8327-EE4F75A63792</imageMediaInstanceId><imageMediaType>14</imageMediaType><relationshipType>15</relationshipType><format>5</format><size>32</size><fileUrl>http://download.xbox.com/content/images/00001000-50e1-b203-c659-b93f4d530a95/1033/thumbm.png</fileUrl><parentGameMediaId>00001000-50E1-B203-C659-B93F4D530A95</parentGameMediaId></image></images><parentProducts><parentProduct><parentProductId>66acd000-77fe-1000-9115-d8024d530a95</parentProductId><parentReducedTitle>Zoo Tycoon</parentReducedTitle><parentSortOrder>0</parentSortOrder></parentProduct></parentProducts><categories><category><categoryId>3000</categoryId><categoryName>Game Genres</categoryName><categorySystemId>3000</categorySystemId></category><category><categoryId>3012</categoryId><categoryName>Strategy &amp; Simulation</categoryName><categorySystemId>3000</categorySystemId><parentCategoryId>3027</parentCategoryId></category><category><categoryId>3025</categoryId><categoryName>Xbox LIVE Marketplace</categoryName><categorySystemId>3000</categorySystemId><parentCategoryId>3000</parentCategoryId></category><category><categoryId>3027</categoryId><categoryName>Xbox LIVE Games</categoryName><categorySystemId>3000</categorySystemId><parentCategoryId>3000</parentCategoryId></category><category><categoryId>3312</categoryId><categoryName>Independent &amp; Music Videos</categoryName><categorySystemId>3000</categorySystemId><parentCategoryId>3025</parentCategoryId></category><category><categoryId>3314</categoryId><categoryName>Music and Short Videos</categoryName><categorySystemId>3000</categorySystemId><parentCategoryId>3312</parentCategoryId></category><category><categoryId>3317</categoryId><categoryName>Xbox 360 Exclusives</categoryName><categorySystemId>3000</categorySystemId><parentCategoryId>3314</parentCategoryId></category><category><categoryId>12001</categoryId><categoryName>Game Publisher Bit 1</categoryName><categorySystemId>12000</categorySystemId></category><category><categoryId>13001</categoryId><categoryName>All Items</categoryName><categorySystemId>13000</categorySystemId></category><category><categoryId>13650</categoryId><categoryName>Props</categoryName><categorySystemId>13000</categorySystemId><parentCategoryId>13001</parentCategoryId></category><category><categoryId>13651</categoryId><categoryName>Prop</categoryName><categorySystemId>13000</categorySystemId><parentCategoryId>13650</parentCategoryId></category></categories><showRating>false</showRating></a:entry></a:feed>