<?xml version="1.0" encoding="UTF-8"?><a:feed xmlns:a="http://www.w3.org/2005/Atom" xmlns="http://marketplace.xboxlive.com/resource/product/v1"><a:author><a:name>Xbox LIVE</a:name></a:author><a:id>http://marketplace.xboxlive.com/resource/product/v1</a:id><a:title>Query Result</a:title><a:updated>0000-00-00 00:00:00Z</a:updated><totalItems>1</totalItems><numItems>1</numItems><locale>en-us</locale><a:entry itemNum="1" xmlns:a="http://www.w3.org/2005/Atom" xmlns="http://marketplace.xboxlive.com/resource/product/v1"><a:title>Sacramento High Top Shoes</a:title><a:id>urn:uuid:00000020-c047-52b1-c517-833758580848</a:id><a:updated>2023-02-07T01:50:03.580Z</a:updated><a:content>game content</a:content><offerInstances><offerInstance><offerId>urn:uuid:00000069-0000-4000-8000-000058580848</offerId><hexOfferId>0x5858084800000069</hexOfferId><offerInstanceId>urn:uuid:28f4a8e5-e173-4799-9b33-108cd9358375</offerInstanceId><startDate>2010-11-18T00:00:00Z</startDate><endDate>2799-12-31T00:00:00Z</endDate><paymentType>2</paymentType><price>160</price><pricetext></pricetext><taxType>0</taxType><tiers><tier>2</tier></tiers><stores><store>1</store></stores><productInstance><productId>00000020-c047-52b1-c517-833758580848</productId><offerLicenseTypeId>12</offerLicenseTypeId><productInstanceId>54e1a4d0-8060-4036-808a-80983b6f3b35</productInstanceId><isAcquirable>1</isAcquirable><isAdSupported>0</isAdSupported><packageSize>52509</packageSize><installSize>6</installSize><packageType>1</packageType><gameRegion>-1</gameRegion><contentId>VOGk0IBgNoqAmDtvOzXDLrwkeVk=</contentId><licenseExtensionBits>0</licenseExtensionBits></productInstance></offerInstance><offerInstance><offerId>urn:uuid:00000069-0000-4000-8000-000058580848</offerId><hexOfferId>0x5858084800000069</hexOfferId><offerInstanceId>urn:uuid:2e3c6457-5e55-4612-afec-1acc82f17f84</offerInstanceId><startDate>2010-12-02T09:00:00Z</startDate><endDate>2799-12-31T00:00:00Z</endDate><paymentType>1</paymentType><price>160</price><pricetext>160¤</pricetext><taxType>0</taxType><tiers><tier>3</tier></tiers><stores><store>1</store></stores><productInstance><productId>00000020-c047-52b1-c517-833758580848</productId><offerLicenseTypeId>12</offerLicenseTypeId><productInstanceId>54e1a4d0-8060-4036-808a-80983b6f3b35</productInstanceId><isAcquirable>1</isAcquirable><isAdSupported>0</isAdSupported><packageSize>52509</packageSize><installSize>6</installSize><packageType>1</packageType><gameRegion>-1</gameRegion><contentId>VOGk0IBgNoqAmDtvOzXDLrwkeVk=</contentId><licenseExtensionBits>0</licenseExtensionBits></productInstance></offerInstance><offerInstance><offerId>urn:uuid:00000069-0000-4000-8000-000058580848</offerId><hexOfferId>0x5858084800000069</hexOfferId><offerInstanceId>urn:uuid:c8ec722e-4b3e-4159-9e6c-3c3c3e1b7747</offerInstanceId><startDate>2010-11-18T00:00:00Z</startDate><endDate>2799-12-31T00:00:00Z</endDate><paymentType>2</paymentType><price>160</price><pricetext></pricetext><taxType>0</taxType><tiers><tier>3</tier></tiers><stores><store>1</store></stores><productInstance><productId>00000020-c047-52b1-c517-833758580848</productId><offerLicenseTypeId>12</offerLicenseTypeId><productInstanceId>54e1a4d0-8060-4036-808a-80983b6f3b35</productInstanceId><isAcquirable>1</isAcquirable><isAdSupported>0</isAdSupported><packageSize>52509</packageSize><installSize>6</installSize><packageType>1</packageType><gameRegion>-1</gameRegion><contentId>VOGk0IBgNoqAmDtvOzXDLrwkeVk=</contentId><licenseExtensionBits>0</licenseExtensionBits></productInstance></offerInstance><offerInstance><offerId>urn:uuid:00000069-0000-4000-8000-000058580848</offerId><hexOfferId>0x5858084800000069</hexOfferId><offerInstanceId>urn:uuid:dd83ecaa-0e4f-48c3-8ecd-66900a08a853</offerInstanceId><startDate>2010-12-02T09:00:00Z</startDate><endDate>2799-12-31T00:00:00Z</endDate><paymentType>1</paymentType><price>160</price><pricetext>160¤</pricetext><taxType>0</taxType><tiers><tier>2</tier></tiers><stores><store>1</store></stores><productInstance><productId>00000020-c047-52b1-c517-833758580848</productId><offerLicenseTypeId>12</offerLicenseTypeId><productInstanceId>54e1a4d0-8060-4036-808a-80983b6f3b35</productInstanceId><isAcquirable>1</isAcquirable><isAdSupported>0</isAdSupported><packageSize>52509</packageSize><installSize>6</installSize><packageType>1</packageType><gameRegion>-1</gameRegion><contentId>VOGk0IBgNoqAmDtvOzXDLrwkeVk=</contentId><licenseExtensionBits>0</licenseExtensionBits></productInstance></offerInstance><offerInstance><offerId>urn:uuid:00000069-0000-4000-8000-000058580848</offerId><hexOfferId>0x5858084800000069</hexOfferId><offerInstanceId>urn:uuid:77c5b30f-18f0-4a6b-840e-8433a1be0cff</offerInstanceId><startDate>2010-12-02T09:00:00Z</startDate><endDate>2799-12-31T00:00:00Z</endDate><paymentType>3</paymentType><price>1.99</price><pricetext>$1.99</pricetext><taxType>0</taxType><tiers><tier>2</tier></tiers><stores><store>1</store></stores><productInstance><productId>00000020-c047-52b1-c517-833758580848</productId><offerLicenseTypeId>12</offerLicenseTypeId><productInstanceId>54e1a4d0-8060-4036-808a-80983b6f3b35</productInstanceId><isAcquirable>1</isAcquirable><isAdSupported>0</isAdSupported><packageSize>52509</packageSize><installSize>6</installSize><packageType>1</packageType><gameRegion>-1</gameRegion><contentId>VOGk0IBgNoqAmDtvOzXDLrwkeVk=</contentId><licenseExtensionBits>0</licenseExtensionBits></productInstance></offerInstance><offerInstance><offerId>urn:uuid:00000069-0000-4000-8000-000058580848</offerId><hexOfferId>0x5858084800000069</hexOfferId><offerInstanceId>urn:uuid:d855b238-fcaa-4db5-b40e-edb249abf218</offerInstanceId><startDate>2010-12-02T09:00:00Z</startDate><endDate>2799-12-31T00:00:00Z</endDate><paymentType>3</paymentType><price>1.99</price><pricetext>$1.99</pricetext><taxType>0</taxType><tiers><tier>3</tier></tiers><stores><store>1</store></stores><productInstance><productId>00000020-c047-52b1-c517-833758580848</productId><offerLicenseTypeId>12</offerLicenseTypeId><productInstanceId>54e1a4d0-8060-4036-808a-80983b6f3b35</productInstanceId><isAcquirable>1</isAcquirable><isAdSupported>0</isAdSupported><packageSize>52509</packageSize><installSize>6</installSize><packageType>1</packageType><gameRegion>-1</gameRegion><contentId>VOGk0IBgNoqAmDtvOzXDLrwkeVk=</contentId><licenseExtensionBits>0</licenseExtensionBits></productInstance></offerInstance></offerInstances><productType>47</productType><reducedTitle>Sacramento High Top Shoes</reducedTitle><reducedDescription>Hit the court or just show your style with these officially licensed NBA kicks!</reducedDescription><fullTitle>Sacramento High Top Shoes</fullTitle><fullDescription>Hit the court or just show your style with these officially licensed NBA kicks!</fullDescription><visibilityDate>2010-12-02T00:00:00</visibilityDate><globalOriginalReleaseDate>2010-12-02T00:00:00</globalOriginalReleaseDate><developerName>Disruptive Publishers</developerName><publisherName>Disruptive Publishers</publisherName><titleId>1482164296</titleId><hexTitleId>0x58580848</hexTitleId><effectiveTitleId>1482164296</effectiveTitleId><gameReducedTitle>NBA Collection</gameReducedTitle><avatarBodyType>1</avatarBodyType><avatarItemAssetId>00000020-C047-52B1-C517-833758580848</avatarItemAssetId><images><image><imageMediaId>A71BC28C-694F-4244-82E3-3BCEC5A0B8E8</imageMediaId><imageMediaInstanceId>89F8B20C-75A8-4CDC-ADDA-CA434B1D5029</imageMediaInstanceId><imageMediaType>14</imageMediaType><relationshipType>33</relationshipType><format>4</format><size>30</size><fileUrl>http://download.xbox.com/content/images/66acd000-77fe-1000-9115-d80258580848/1033/boxartsm.jpg</fileUrl><parentGameMediaId>66ACD000-77FE-1000-9115-D80258580848</parentGameMediaId></image><image><imageMediaId>A19F5B23-0A26-4CB5-82E0-35CB4289349B</imageMediaId><imageMediaInstanceId>020468FB-180A-4762-8F02-E88EF300D2B6</imageMediaInstanceId><imageMediaType>14</imageMediaType><relationshipType>33</relationshipType><format>4</format><size>23</size><fileUrl>http://download.xbox.com/content/images/66acd000-77fe-1000-9115-d80258580848/1033/boxartlg.jpg</fileUrl><parentGameMediaId>66ACD000-77FE-1000-9115-D80258580848</parentGameMediaId></image><image><imageMediaId>1AB18BEB-1408-43C0-90A9-E155D77051A9</imageMediaId><imageMediaInstanceId>21A22441-A4A1-4847-91C9-25578D8D40C2</imageMediaInstanceId><imageMediaType>14</imageMediaType><relationshipType>33</relationshipType><format>4</format><size>23</size><fileUrl>http://download.xbox.com/content/images/66acd000-77fe-1000-9115-d802584d07d1/1033/boxartlg.jpg</fileUrl><parentGameMediaId>66ACD000-77FE-1000-9115-D802584D07D1</parentGameMediaId></image><image><imageMediaId>96B124A9-6605-43EF-96B9-9191F8B80987</imageMediaId><imageMediaInstanceId>36ED4903-5A05-4847-BD2E-327B8AADC5D5</imageMediaInstanceId><imageMediaType>14</imageMediaType><relationshipType>15</relationshipType><format>5</format><size>32</size><fileUrl>http://download.xbox.com/content/images/00000020-c047-52b1-c517-833758580848/1033/thumbm.png</fileUrl><parentGameMediaId>00000020-C047-52B1-C517-833758580848</parentGameMediaId></image><image><imageMediaId>C2937374-32D6-4632-8423-E23DEF559F41</imageMediaId><imageMediaInstanceId>8AC2ED28-190B-4AA0-9D80-66684FC47F79</imageMediaInstanceId><imageMediaType>14</imageMediaType><relationshipType>27</relationshipType><format>5</format><size>15</size><fileUrl>http://download.xbox.com/content/images/00000020-c047-52b1-c517-833758580848/1033/banner.png</fileUrl><parentGameMediaId>00000020-C047-52B1-C517-833758580848</parentGameMediaId></image><image><imageMediaId>35821D06-0B7C-444A-BF1C-BA17EE65770C</imageMediaId><imageMediaInstanceId>CBA2A729-71D3-4A10-A5B7-91072AF296A8</imageMediaInstanceId><imageMediaType>14</imageMediaType><relationshipType>33</relationshipType><format>4</format><size>30</size><fileUrl>http://download.xbox.com/content/images/66acd000-77fe-1000-9115-d802584d07d1/1033/boxartsm.jpg</fileUrl><parentGameMediaId>66ACD000-77FE-1000-9115-D802584D07D1</parentGameMediaId></image><image><imageMediaId>FECFECF8-DDE7-45C8-A2B5-4C2967FEFCD3</imageMediaId><imageMediaInstanceId>75B80178-DA0A-4096-86FA-DA48D1E919DF</imageMediaInstanceId><imageMediaType>14</imageMediaType><relationshipType>15</relationshipType><format>5</format><size>14</size><fileUrl>http://download.xbox.com/content/images/00000020-c047-52b1-c517-833758580848/1033/thumbsm.png</fileUrl><parentGameMediaId>00000020-C047-52B1-C517-833758580848</parentGameMediaId></image><image><imageMediaId>0A741564-52E4-496E-B9CC-FF213E05AC04</imageMediaId><imageMediaInstanceId>B445FFE3-79E7-4E91-BD54-EF56A65A830E</imageMediaInstanceId><imageMediaType>14</imageMediaType><relationshipType>15</relationshipType><format>5</format><size>25</size><fileUrl>http://download.xbox.com/content/images/00000020-c047-52b1-c517-833758580848/1033/thumblg.png</fileUrl><parentGameMediaId>00000020-C047-52B1-C517-833758580848</parentGameMediaId></image></images><categories><category><categoryId>3000</categoryId><categoryName>Game Genres</categoryName><categorySystemId>3000</categorySystemId></category><category><categoryId>3025</categoryId><categoryName>Xbox LIVE Marketplace</categoryName><categorySystemId>3000</categorySystemId><parentCategoryId>3000</parentCategoryId></category><category><categoryId>3312</categoryId><categoryName>Independent &amp; Music Videos</categoryName><categorySystemId>3000</categorySystemId><parentCategoryId>3025</parentCategoryId></category><category><categoryId>3314</categoryId><categoryName>Music and Short Videos</categoryName><categorySystemId>3000</categorySystemId><parentCategoryId>3312</parentCategoryId></category><category><categoryId>3315</categoryId><categoryName>Sports</categoryName><categorySystemId>3000</categorySystemId><parentCategoryId>3314</parentCategoryId></category><category><categoryId>3317</categoryId><categoryName>Xbox 360 Exclusives</categoryName><categorySystemId>3000</categorySystemId><parentCategoryId>3314</parentCategoryId></category><category><categoryId>12001</categoryId><categoryName>Game Publisher Bit 1</categoryName><categorySystemId>12000</categorySystemId></category><category><categoryId>13001</categoryId><categoryName>All Items</categoryName><categorySystemId>13000</categorySystemId></category><category><categoryId>13300</categoryId><categoryName>Shoes</categoryName><categorySystemId>13000</categorySystemId><parentCategoryId>13001</parentCategoryId></category><category><categoryId>13304</categoryId><categoryName>Formal Shoes</categoryName><categorySystemId>13000</categorySystemId><parentCategoryId>13300</parentCategoryId></category><category><categoryId>14001</categoryId><categoryName>Life Style</categoryName><categorySystemId>14000</categorySystemId></category><category><categoryId>14108</categoryId><categoryName>NBA Collection</categoryName><categorySystemId>14000</categorySystemId><parentCategoryId>14001</parentCategoryId></category><category><categoryId>14134</categoryId><categoryName>Sacramento Kings</categoryName><categorySystemId>14000</categorySystemId><parentCategoryId>14108</parentCategoryId></category></categories><showRating>false</showRating></a:entry></a:feed>