<?xml version="1.0" encoding="UTF-8"?><a:feed xmlns:a="http://www.w3.org/2005/Atom" xmlns="http://marketplace.xboxlive.com/resource/product/v1"><a:author><a:name>Xbox LIVE</a:name></a:author><a:id>http://marketplace.xboxlive.com/resource/product/v1</a:id><a:title>Query Result</a:title><a:updated>0000-00-00 00:00:00Z</a:updated><totalItems>1</totalItems><numItems>1</numItems><locale>en-us</locale><a:entry itemNum="1" xmlns:a="http://www.w3.org/2005/Atom" xmlns="http://marketplace.xboxlive.com/resource/product/v1"><a:title>"Pardon Me" (pro) - Incubus</a:title><a:id>urn:uuid:2bd32762-968c-4376-a888-76eec0cd8e6c</a:id><a:updated>2023-02-03T18:00:03.647Z</a:updated><a:content>game content</a:content><offerInstances></offerInstances><productType>18</productType><reducedTitle>"Pardon Me" (pro) - Incubus</reducedTitle><reducedDescription>(Music Downloads Not Rated by the ESRB) Build your Rock Band 3 library by purchasing this song game Pro Guitar and Bass upgrade: "Pardon Me" (pro) -- Incubus. In order to play Rock Band Pro Guitar downloadable song upgrade you will need the Rock Band 3 game disc, a Pro Guitar peripheral, and the basic song track. Not all Rock Band Music Store or export songs support Pro Guitar. Please visit www.rockband.com for more information.</reducedDescription><fullTitle>"Pardon Me" (pro) - Incubus</fullTitle><fullDescription>(Music Downloads Not Rated by the ESRB) Build your Rock Band 3 library by purchasing this song game Pro Guitar and Bass upgrade: "Pardon Me" (pro) -- Incubus. In order to play Rock Band Pro Guitar downloadable song upgrade you will need the Rock Band 3 game disc, a Pro Guitar peripheral, and the basic song track. Not all Rock Band Music Store or export songs support Pro Guitar. Please visit www.rockband.com for more information. </fullDescription><visibilityDate>2011-08-16T00:00:00</visibilityDate><globalOriginalReleaseDate>2011-08-23T00:00:00</globalOriginalReleaseDate><ratingId>30</ratingId><developerName>Harmonix Music Systems, Inc.</developerName><publisherName>Mad Catz</publisherName><titleId>1161890068</titleId><hexTitleId>0x45410914</hexTitleId><effectiveTitleId>1161890068</effectiveTitleId><gameReducedTitle>Rock Band 3</gameReducedTitle><images><image><imageMediaId>182B0F73-3ED9-4BE5-A84D-6AEB66F09B77</imageMediaId><imageMediaInstanceId>234F2306-7B1B-474C-A7D2-085F0132FE02</imageMediaInstanceId><imageMediaType>14</imageMediaType><relationshipType>33</relationshipType><format>4</format><size>23</size><fileUrl>http://download.xbox.com/content/images/66acd000-77fe-1000-9115-d80245410914/1033/boxartlg.jpg</fileUrl><parentGameMediaId>66ACD000-77FE-1000-9115-D80245410914</parentGameMediaId></image><image><imageMediaId>320AF383-68CA-4216-BBA8-C203312372CA</imageMediaId><imageMediaInstanceId>15635AF1-1205-4C14-8E93-793ED8DB23AC</imageMediaInstanceId><imageMediaType>14</imageMediaType><relationshipType>33</relationshipType><format>4</format><size>30</size><fileUrl>http://download.xbox.com/content/images/66acd000-77fe-1000-9115-d80245410914/1033/boxartsm.jpg</fileUrl><parentGameMediaId>66ACD000-77FE-1000-9115-D80245410914</parentGameMediaId></image><image><imageMediaId>485AF3B5-F088-404D-9CD7-AEB3E7FB4E85</imageMediaId><imageMediaInstanceId>B167F4E9-3BD4-4ECE-BC99-184ECB05301E</imageMediaInstanceId><imageMediaType>14</imageMediaType><relationshipType>23</relationshipType><format>5</format><size>14</size><fileUrl>http://download.xbox.com/content/images/2bd32762-968c-4376-a888-76eec0cd8e6c/1033/tile.png</fileUrl><parentGameMediaId>2BD32762-968C-4376-A888-76EEC0CD8E6C</parentGameMediaId></image><image><imageMediaId>D10BB834-2CEC-45A6-A4F4-C3853C9A98FB</imageMediaId><imageMediaInstanceId>4D40F889-E39D-4EE7-82DF-3B385381D268</imageMediaInstanceId><imageMediaType>14</imageMediaType><relationshipType>25</relationshipType><format>4</format><size>22</size><fileUrl>http://download.xbox.com/content/images/2bd32762-968c-4376-a888-76eec0cd8e6c/1033/background.jpg</fileUrl><parentGameMediaId>2BD32762-968C-4376-A888-76EEC0CD8E6C</parentGameMediaId></image><image><imageMediaId>27C85A9D-F1FC-41E8-9250-071C8D601869</imageMediaId><imageMediaInstanceId>A9A2E042-8F60-422F-958D-3E02F23723D9</imageMediaInstanceId><imageMediaType>14</imageMediaType><relationshipType>33</relationshipType><format>4</format><size>30</size><fileUrl>http://download.xbox.com/content/images/2bd32762-968c-4376-a888-76eec0cd8e6c/1033/boxartsm.jpg</fileUrl><parentGameMediaId>2BD32762-968C-4376-A888-76EEC0CD8E6C</parentGameMediaId></image><image><imageMediaId>75327A8B-53CE-4388-955A-43133FFFE005</imageMediaId><imageMediaInstanceId>A9AFD318-E917-4B75-B54B-5688DBED5DBA</imageMediaInstanceId><imageMediaType>14</imageMediaType><relationshipType>33</relationshipType><format>4</format><size>30</size><fileUrl>http://download.xbox.com/content/images/66acd000-77fe-1000-9115-d802545607d5/1033/boxartsm.jpg</fileUrl><parentGameMediaId>66ACD000-77FE-1000-9115-D802545607D5</parentGameMediaId></image><image><imageMediaId>B794E1F4-8ADA-4182-B575-9CC80FA89F3F</imageMediaId><imageMediaInstanceId>BF08A47B-9FFA-4BDF-B8AF-73780724342C</imageMediaInstanceId><imageMediaType>14</imageMediaType><relationshipType>27</relationshipType><format>5</format><size>15</size><fileUrl>http://download.xbox.com/content/images/2bd32762-968c-4376-a888-76eec0cd8e6c/1033/banner.png</fileUrl><parentGameMediaId>2BD32762-968C-4376-A888-76EEC0CD8E6C</parentGameMediaId></image><image><imageMediaId>BC9DC6E4-3725-40BB-91E8-37151CCA4BB2</imageMediaId><imageMediaInstanceId>FD4E6A40-9C5F-489C-B5B6-FB3570D4EE01</imageMediaInstanceId><imageMediaType>14</imageMediaType><relationshipType>33</relationshipType><format>4</format><size>23</size><fileUrl>http://download.xbox.com/content/images/66acd000-77fe-1000-9115-d802545607d5/1033/boxartlg.jpg</fileUrl><parentGameMediaId>66ACD000-77FE-1000-9115-D802545607D5</parentGameMediaId></image><image><imageMediaId>4A46EEC7-89B4-41B1-A6E8-87483C652C99</imageMediaId><imageMediaInstanceId>42CB8920-6DF8-4477-933B-FD0300D06171</imageMediaInstanceId><imageMediaType>14</imageMediaType><relationshipType>33</relationshipType><format>4</format><size>23</size><fileUrl>http://download.xbox.com/content/images/2bd32762-968c-4376-a888-76eec0cd8e6c/1033/boxartlg.jpg</fileUrl><parentGameMediaId>2BD32762-968C-4376-A888-76EEC0CD8E6C</parentGameMediaId></image></images><slideShows><slideShow><image><displayOrder>1</displayOrder><imageMediaId>C6A2E179-34C6-428F-8543-9136683DD133</imageMediaId><imageMediaInstanceId>0B6E374B-ABF3-4655-A021-167B1E6DE6D3</imageMediaInstanceId><imageMediaType>14</imageMediaType><relationshipType>32</relationshipType><format>4</format><size>27</size><fileUrl>http://download.xbox.com/content/images/2bd32762-968c-4376-a888-76eec0cd8e6c/1033/screenlg1.jpg</fileUrl></image><image><displayOrder>2</displayOrder><imageMediaId>0A8C0BAD-1319-4280-B951-656489FA0AA5</imageMediaId><imageMediaInstanceId>EF7CECCD-0E08-4A04-9018-260BA45A2BCE</imageMediaInstanceId><imageMediaType>14</imageMediaType><relationshipType>32</relationshipType><format>4</format><size>27</size><fileUrl>http://download.xbox.com/content/images/2bd32762-968c-4376-a888-76eec0cd8e6c/1033/screenlg2.jpg</fileUrl></image><image><displayOrder>3</displayOrder><imageMediaId>5B5CF862-EC51-44FE-BD93-44B6EB11558D</imageMediaId><imageMediaInstanceId>D1289A2E-7FB7-4E2C-B36B-DDE677794890</imageMediaInstanceId><imageMediaType>14</imageMediaType><relationshipType>32</relationshipType><format>4</format><size>27</size><fileUrl>http://download.xbox.com/content/images/2bd32762-968c-4376-a888-76eec0cd8e6c/1033/screenlg3.jpg</fileUrl></image><image><displayOrder>4</displayOrder><imageMediaId>C311416C-7AFB-426A-88A6-746C4566F75F</imageMediaId><imageMediaInstanceId>37DC4131-7CF5-44C0-9264-68257D9C2EEE</imageMediaInstanceId><imageMediaType>14</imageMediaType><relationshipType>32</relationshipType><format>4</format><size>27</size><fileUrl>http://download.xbox.com/content/images/2bd32762-968c-4376-a888-76eec0cd8e6c/1033/screenlg4.jpg</fileUrl></image></slideShow></slideShows><parentProducts><parentProduct><parentProductId>66acd000-77fe-1000-9115-d80245410914</parentProductId><parentReducedTitle>Rock Band 3</parentReducedTitle><parentSortOrder>0</parentSortOrder></parentProduct><parentProduct><parentProductId>66acd000-77fe-1000-9115-d802545607d5</parentProductId><parentReducedTitle>Rock Band Music Store</parentReducedTitle><parentSortOrder>1</parentSortOrder></parentProduct></parentProducts><categories><category><categoryId>3000</categoryId><categoryName>Game Genres</categoryName><categorySystemId>3000</categorySystemId></category><category><categoryId>3001</categoryId><categoryName>Other</categoryName><categorySystemId>3000</categorySystemId><parentCategoryId>3027</parentCategoryId></category><category><categoryId>3007</categoryId><categoryName>Music</categoryName><categorySystemId>3000</categorySystemId><parentCategoryId>3027</parentCategoryId></category><category><categoryId>3012</categoryId><categoryName>Strategy &amp; Simulation</categoryName><categorySystemId>3000</categorySystemId><parentCategoryId>3027</parentCategoryId></category><category><categoryId>3027</categoryId><categoryName>Xbox LIVE Games</categoryName><categorySystemId>3000</categorySystemId><parentCategoryId>3000</parentCategoryId></category><category><categoryId>12001</categoryId><categoryName>Game Publisher Bit 1</categoryName><categorySystemId>12000</categorySystemId></category></categories></a:entry></a:feed>