<?xml version="1.0" encoding="UTF-8"?><a:feed xmlns:a="http://www.w3.org/2005/Atom" xmlns="http://marketplace.xboxlive.com/resource/product/v1"><a:author><a:name>Xbox LIVE</a:name></a:author><a:id>http://marketplace.xboxlive.com/resource/product/v1</a:id><a:title>Query Result</a:title><a:updated>0000-00-00 00:00:00Z</a:updated><totalItems>1</totalItems><numItems>1</numItems><locale>en-us</locale><a:entry itemNum="1" xmlns:a="http://www.w3.org/2005/Atom" xmlns="http://marketplace.xboxlive.com/resource/product/v1"><a:title>NCAA® Football 13 Online Pass</a:title><a:id>urn:uuid:5481fe24-77e1-4a8c-b138-23f378a72f19</a:id><a:updated>2014-08-10T00:00:00.957Z</a:updated><a:content>game content</a:content><offerInstances><offerInstance><offerId>urn:uuid:10e66400-0000-4000-8000-00004541098a</offerId><hexOfferId>0x4541098a10e66400</hexOfferId><offerInstanceId>urn:uuid:fa3270c7-4f2d-4141-83c2-08733df4a00b</offerInstanceId><startDate>2012-05-14T09:00:00Z</startDate><endDate>2014-08-10T00:00:00Z</endDate><paymentType>2</paymentType><price>0</price><pricetext></pricetext><taxType>0</taxType><tiers><tier>2</tier></tiers><stores><store>1</store></stores><productInstance><productId>e5330acc-c31e-4d1e-b49f-a828af8a0a5e</productId><offerLicenseTypeId>14</offerLicenseTypeId><productInstanceId>53c56303-0bd0-4014-808f-8fd7c9cb50f7</productInstanceId><isAcquirable>1</isAcquirable><isAdSupported>0</isAdSupported><packageSize>15811</packageSize><installSize>4</installSize><packageType>1</packageType><gameRegion>16776703</gameRegion><contentId>U8VjAwvQFI+P18nLUPcGsCK4S9g=</contentId><licenseExtensionBits>1</licenseExtensionBits></productInstance></offerInstance><offerInstance><offerId>urn:uuid:10e66400-0000-4000-8000-00004541098a</offerId><hexOfferId>0x4541098a10e66400</hexOfferId><offerInstanceId>urn:uuid:80521ee7-a080-423d-ad6a-529f74e3b97a</offerInstanceId><startDate>2012-05-14T09:00:00Z</startDate><endDate>2014-08-10T00:00:00Z</endDate><paymentType>2</paymentType><price>0</price><pricetext></pricetext><taxType>0</taxType><tiers><tier>3</tier></tiers><stores><store>1</store></stores><productInstance><productId>e5330acc-c31e-4d1e-b49f-a828af8a0a5e</productId><offerLicenseTypeId>14</offerLicenseTypeId><productInstanceId>53c56303-0bd0-4014-808f-8fd7c9cb50f7</productInstanceId><isAcquirable>1</isAcquirable><isAdSupported>0</isAdSupported><packageSize>15811</packageSize><installSize>4</installSize><packageType>1</packageType><gameRegion>16776703</gameRegion><contentId>U8VjAwvQFI+P18nLUPcGsCK4S9g=</contentId><licenseExtensionBits>1</licenseExtensionBits></productInstance></offerInstance><offerInstance><offerId>urn:uuid:10e66400-0000-4000-8000-00004541098a</offerId><hexOfferId>0x4541098a10e66400</hexOfferId><offerInstanceId>urn:uuid:c2652beb-1e80-4d44-acc5-58e348c5bfde</offerInstanceId><startDate>2012-06-20T09:00:00Z</startDate><endDate>2014-08-10T00:00:00Z</endDate><paymentType>3</paymentType><price>0</price><pricetext>$0.00</pricetext><taxType>0</taxType><tiers><tier>3</tier></tiers><stores><store>1</store></stores><productInstance><productId>e5330acc-c31e-4d1e-b49f-a828af8a0a5e</productId><offerLicenseTypeId>14</offerLicenseTypeId><productInstanceId>53c56303-0bd0-4014-808f-8fd7c9cb50f7</productInstanceId><isAcquirable>1</isAcquirable><isAdSupported>0</isAdSupported><packageSize>15811</packageSize><installSize>4</installSize><packageType>1</packageType><gameRegion>16776703</gameRegion><contentId>U8VjAwvQFI+P18nLUPcGsCK4S9g=</contentId><licenseExtensionBits>1</licenseExtensionBits></productInstance></offerInstance><offerInstance><offerId>urn:uuid:10e66400-0000-4000-8000-00004541098a</offerId><hexOfferId>0x4541098a10e66400</hexOfferId><offerInstanceId>urn:uuid:d8324466-abef-4e8a-83b5-79dbbd13f4fa</offerInstanceId><startDate>2012-06-20T09:00:00Z</startDate><endDate>2014-08-10T00:00:00Z</endDate><paymentType>1</paymentType><price>0</price><pricetext>0¤</pricetext><taxType>0</taxType><tiers><tier>3</tier></tiers><stores><store>1</store></stores><productInstance><productId>e5330acc-c31e-4d1e-b49f-a828af8a0a5e</productId><offerLicenseTypeId>14</offerLicenseTypeId><productInstanceId>53c56303-0bd0-4014-808f-8fd7c9cb50f7</productInstanceId><isAcquirable>1</isAcquirable><isAdSupported>0</isAdSupported><packageSize>15811</packageSize><installSize>4</installSize><packageType>1</packageType><gameRegion>16776703</gameRegion><contentId>U8VjAwvQFI+P18nLUPcGsCK4S9g=</contentId><licenseExtensionBits>1</licenseExtensionBits></productInstance></offerInstance><offerInstance><offerId>urn:uuid:10e66400-0000-4000-8000-00004541098a</offerId><hexOfferId>0x4541098a10e66400</hexOfferId><offerInstanceId>urn:uuid:03544054-50ca-45a4-bfd3-c7e87674a12f</offerInstanceId><startDate>2012-06-20T09:00:00Z</startDate><endDate>2014-08-10T00:00:00Z</endDate><paymentType>1</paymentType><price>0</price><pricetext>0¤</pricetext><taxType>0</taxType><tiers><tier>2</tier></tiers><stores><store>1</store></stores><productInstance><productId>e5330acc-c31e-4d1e-b49f-a828af8a0a5e</productId><offerLicenseTypeId>14</offerLicenseTypeId><productInstanceId>53c56303-0bd0-4014-808f-8fd7c9cb50f7</productInstanceId><isAcquirable>1</isAcquirable><isAdSupported>0</isAdSupported><packageSize>15811</packageSize><installSize>4</installSize><packageType>1</packageType><gameRegion>16776703</gameRegion><contentId>U8VjAwvQFI+P18nLUPcGsCK4S9g=</contentId><licenseExtensionBits>1</licenseExtensionBits></productInstance></offerInstance><offerInstance><offerId>urn:uuid:10e66400-0000-4000-8000-00004541098a</offerId><hexOfferId>0x4541098a10e66400</hexOfferId><offerInstanceId>urn:uuid:14d0238b-0a26-4135-8d07-fe93af3e7169</offerInstanceId><startDate>2012-06-20T09:00:00Z</startDate><endDate>2014-08-10T00:00:00Z</endDate><paymentType>3</paymentType><price>0</price><pricetext>$0.00</pricetext><taxType>0</taxType><tiers><tier>2</tier></tiers><stores><store>1</store></stores><productInstance><productId>e5330acc-c31e-4d1e-b49f-a828af8a0a5e</productId><offerLicenseTypeId>14</offerLicenseTypeId><productInstanceId>53c56303-0bd0-4014-808f-8fd7c9cb50f7</productInstanceId><isAcquirable>1</isAcquirable><isAdSupported>0</isAdSupported><packageSize>15811</packageSize><installSize>4</installSize><packageType>1</packageType><gameRegion>16776703</gameRegion><contentId>U8VjAwvQFI+P18nLUPcGsCK4S9g=</contentId><licenseExtensionBits>1</licenseExtensionBits></productInstance></offerInstance></offerInstances><productType>18</productType><reducedTitle>NCAA® Football 13 Online Pass</reducedTitle><reducedDescription>Want to be able to play head to head games or Online Dynasty? With this entitlement you’ll have access to the online features of NCAA Football 13. Play ranked games to try and climb up the Online Leader boards, download TeamBuilder teams for use in modes like Dynasty and Play Now, or play against up to 11 other players to build the ultimate dynasty in Online Dynasty mode. </reducedDescription><fullTitle>NCAA® Football 13 Online Pass</fullTitle><fullDescription>Want to be able to play head to head games or Online Dynasty? With this entitlement you’ll have access to the online features of NCAA Football 13. Play ranked games to try and climb up the Online Leader boards, download TeamBuilder teams for use in modes like Dynasty and Play Now, or play against up to 11 other players to build the ultimate dynasty in Online Dynasty mode. </fullDescription><voiceDisplayTitle>NCAA Football 13 Online Pass</voiceDisplayTitle><visibilityDate>2012-05-01T00:00:00</visibilityDate><globalOriginalReleaseDate>2012-07-10T00:00:00</globalOriginalReleaseDate><ratingId>10</ratingId><developerName>EA Tiburon</developerName><publisherName>EA SPORTS</publisherName><titleId>1161890186</titleId><hexTitleId>0x4541098a</hexTitleId><effectiveTitleId>1161890186</effectiveTitleId><gameReducedTitle>NCAA® Football 13</gameReducedTitle><images><image><imageMediaId>0E5107BD-7C91-4ACD-A0EF-8A4A1A028BB8</imageMediaId><imageMediaInstanceId>9905AB95-1F87-49DC-A7F7-8F455082CF67</imageMediaInstanceId><imageMediaType>14</imageMediaType><relationshipType>33</relationshipType><format>4</format><size>23</size><fileUrl>http://download.xbox.com/content/images/66acd000-77fe-1000-9115-d8024541098a/1033/boxartlg.jpg</fileUrl><parentGameMediaId>66ACD000-77FE-1000-9115-D8024541098A</parentGameMediaId></image><image><imageMediaId>DA0091D7-61BE-4E2C-9A5E-74BC0B69C95F</imageMediaId><imageMediaInstanceId>4CE1D753-CB8C-4EDD-AE7C-D0FBFA1476C8</imageMediaInstanceId><imageMediaType>14</imageMediaType><relationshipType>33</relationshipType><format>4</format><size>30</size><fileUrl>http://download.xbox.com/content/images/66acd000-77fe-1000-9115-d8024541098a/1033/boxartsm.jpg</fileUrl><parentGameMediaId>66ACD000-77FE-1000-9115-D8024541098A</parentGameMediaId></image><image><imageMediaId>D8AB5CD3-89C0-4F34-B52F-2E0719D52658</imageMediaId><imageMediaInstanceId>BE19CDE8-8D87-428F-8FEF-08616BAFE5C2</imageMediaInstanceId><imageMediaType>14</imageMediaType><relationshipType>33</relationshipType><format>4</format><size>30</size><fileUrl>http://download.xbox.com/content/images/5481fe24-77e1-4a8c-b138-23f378a72f19/1033/boxartsm.jpg</fileUrl><parentGameMediaId>5481FE24-77E1-4A8C-B138-23F378A72F19</parentGameMediaId></image><image><imageMediaId>B39DD149-609D-4D25-8BAE-5B986FE18437</imageMediaId><imageMediaInstanceId>175BF88A-52A7-4E7B-8E5A-6E6A035528BA</imageMediaInstanceId><imageMediaType>14</imageMediaType><relationshipType>33</relationshipType><format>4</format><size>23</size><fileUrl>http://download.xbox.com/content/images/5481fe24-77e1-4a8c-b138-23f378a72f19/1033/boxartlg.jpg</fileUrl><parentGameMediaId>5481FE24-77E1-4A8C-B138-23F378A72F19</parentGameMediaId></image><image><imageMediaId>21807488-A4DD-46F9-A33C-9B34F54100F9</imageMediaId><imageMediaInstanceId>906AE07E-C8F3-4415-ADC8-D1F979ECE736</imageMediaInstanceId><imageMediaType>14</imageMediaType><relationshipType>25</relationshipType><format>4</format><size>22</size><fileUrl>http://download.xbox.com/content/images/5481fe24-77e1-4a8c-b138-23f378a72f19/1033/background.jpg</fileUrl><parentGameMediaId>5481FE24-77E1-4A8C-B138-23F378A72F19</parentGameMediaId></image><image><imageMediaId>6E3CA76B-BDDF-44D7-88FB-2C293DBB3D3E</imageMediaId><imageMediaInstanceId>CEA24B49-BA56-436B-BADE-F8E9F3C3CFFE</imageMediaInstanceId><imageMediaType>14</imageMediaType><relationshipType>23</relationshipType><format>5</format><size>14</size><fileUrl>http://download.xbox.com/content/images/5481fe24-77e1-4a8c-b138-23f378a72f19/1033/tile.png</fileUrl><parentGameMediaId>5481FE24-77E1-4A8C-B138-23F378A72F19</parentGameMediaId></image><image><imageMediaId>7BD43FB7-76E5-4D3F-A0D9-C1BACA0E7391</imageMediaId><imageMediaInstanceId>A0844A1B-516C-46D9-8DE3-FCFF642FE96E</imageMediaInstanceId><imageMediaType>14</imageMediaType><relationshipType>27</relationshipType><format>5</format><size>15</size><fileUrl>http://download.xbox.com/content/images/5481fe24-77e1-4a8c-b138-23f378a72f19/1033/banner.png</fileUrl><parentGameMediaId>5481FE24-77E1-4A8C-B138-23F378A72F19</parentGameMediaId></image></images><parentProducts><parentProduct><parentProductId>66acd000-77fe-1000-9115-d8024541098a</parentProductId><parentReducedTitle>NCAA® Football 13</parentReducedTitle><parentSortOrder>0</parentSortOrder></parentProduct></parentProducts><categories><category><categoryId>3000</categoryId><categoryName>Game Genres</categoryName><categorySystemId>3000</categorySystemId></category><category><categoryId>3013</categoryId><categoryName>Sports &amp; Recreation</categoryName><categorySystemId>3000</categorySystemId><parentCategoryId>3027</parentCategoryId></category><category><categoryId>3025</categoryId><categoryName>Xbox LIVE Marketplace</categoryName><categorySystemId>3000</categorySystemId><parentCategoryId>3000</parentCategoryId></category><category><categoryId>3027</categoryId><categoryName>Xbox LIVE Games</categoryName><categorySystemId>3000</categorySystemId><parentCategoryId>3000</parentCategoryId></category><category><categoryId>3312</categoryId><categoryName>Independent &amp; Music Videos</categoryName><categorySystemId>3000</categorySystemId><parentCategoryId>3025</parentCategoryId></category><category><categoryId>3314</categoryId><categoryName>Music and Short Videos</categoryName><categorySystemId>3000</categorySystemId><parentCategoryId>3312</parentCategoryId></category><category><categoryId>3315</categoryId><categoryName>Sports</categoryName><categorySystemId>3000</categorySystemId><parentCategoryId>3314</parentCategoryId></category><category><categoryId>12001</categoryId><categoryName>Game Publisher Bit 1</categoryName><categorySystemId>12000</categorySystemId></category></categories></a:entry></a:feed>