<?xml version="1.0" encoding="UTF-8"?><a:feed xmlns:a="http://www.w3.org/2005/Atom" xmlns="http://marketplace.xboxlive.com/resource/product/v1"><a:author><a:name>Xbox LIVE</a:name></a:author><a:id>http://marketplace.xboxlive.com/resource/product/v1</a:id><a:title>Query Result</a:title><a:updated>0000-00-00 00:00:00Z</a:updated><totalItems>1</totalItems><numItems>1</numItems><locale>en-us</locale><a:entry itemNum="1" xmlns:a="http://www.w3.org/2005/Atom" xmlns="http://marketplace.xboxlive.com/resource/product/v1"><a:title>Sonic the Fighters</a:title><a:id>urn:uuid:66acd000-77fe-1000-9115-d8025841129e</a:id><a:updated>2023-04-21T22:22:24.063Z</a:updated><a:content>game content</a:content><offerInstances><offerInstance><offerId>urn:uuid:00000001-0000-4000-8000-00005841129e</offerId><hexOfferId>0x5841129e00000001</hexOfferId><offerInstanceId>urn:uuid:5720d4d3-a55c-468b-9c3d-390fcb1a2246</offerInstanceId><startDate>2012-11-28T09:00:00Z</startDate><endDate>2799-12-31T00:00:00Z</endDate><paymentType>1</paymentType><price>400</price><pricetext>400¤</pricetext><taxType>0</taxType><tiers><tier>3</tier></tiers><stores><store>1</store></stores><productInstance><productId>66acd000-77fe-1000-9115-d8025841129e</productId><offerLicenseTypeId>14</offerLicenseTypeId><productInstanceId>17db4b59-7093-4006-801b-64bfc3e0bcb0</productInstanceId><isAcquirable>1</isAcquirable><isAdSupported>0</isAdSupported><packageSize>100216781</packageSize><installSize>6218</installSize><packageType>1</packageType><gameRegion>16776703</gameRegion><contentId>F9tLWXCTBhtkv8PgvLAAv/FOrLs=</contentId><licenseExtensionBits>1</licenseExtensionBits></productInstance></offerInstance><offerInstance><offerId>urn:uuid:00000001-0000-4000-8000-00005841129e</offerId><hexOfferId>0x5841129e00000001</hexOfferId><offerInstanceId>urn:uuid:84c0a0e9-a621-42d3-892d-432163b57876</offerInstanceId><startDate>2012-11-28T09:00:00Z</startDate><endDate>2799-12-31T00:00:00Z</endDate><paymentType>3</paymentType><price>4.99</price><pricetext>$4.99</pricetext><taxType>0</taxType><tiers><tier>3</tier></tiers><stores><store>1</store></stores><productInstance><productId>66acd000-77fe-1000-9115-d8025841129e</productId><offerLicenseTypeId>14</offerLicenseTypeId><productInstanceId>17db4b59-7093-4006-801b-64bfc3e0bcb0</productInstanceId><isAcquirable>1</isAcquirable><isAdSupported>0</isAdSupported><packageSize>100216781</packageSize><installSize>6218</installSize><packageType>1</packageType><gameRegion>16776703</gameRegion><contentId>F9tLWXCTBhtkv8PgvLAAv/FOrLs=</contentId><licenseExtensionBits>1</licenseExtensionBits></productInstance></offerInstance><offerInstance><offerId>urn:uuid:00000001-0000-4000-8000-00005841129e</offerId><hexOfferId>0x5841129e00000001</hexOfferId><offerInstanceId>urn:uuid:30ba0917-918b-4871-ae42-88f9f59d3ac8</offerInstanceId><startDate>2012-11-28T09:00:00Z</startDate><endDate>2799-12-31T00:00:00Z</endDate><paymentType>1</paymentType><price>400</price><pricetext>400¤</pricetext><taxType>0</taxType><tiers><tier>2</tier></tiers><stores><store>1</store></stores><productInstance><productId>66acd000-77fe-1000-9115-d8025841129e</productId><offerLicenseTypeId>14</offerLicenseTypeId><productInstanceId>17db4b59-7093-4006-801b-64bfc3e0bcb0</productInstanceId><isAcquirable>1</isAcquirable><isAdSupported>0</isAdSupported><packageSize>100216781</packageSize><installSize>6218</installSize><packageType>1</packageType><gameRegion>16776703</gameRegion><contentId>F9tLWXCTBhtkv8PgvLAAv/FOrLs=</contentId><licenseExtensionBits>1</licenseExtensionBits></productInstance></offerInstance><offerInstance><offerId>urn:uuid:00000001-0000-4000-8000-00005841129e</offerId><hexOfferId>0x5841129e00000001</hexOfferId><offerInstanceId>urn:uuid:4ec813a7-735c-4e73-a540-97a78ddcce05</offerInstanceId><startDate>2012-11-28T09:00:00Z</startDate><endDate>2799-12-31T00:00:00Z</endDate><paymentType>3</paymentType><price>4.99</price><pricetext>$4.99</pricetext><taxType>0</taxType><tiers><tier>2</tier></tiers><stores><store>1</store></stores><productInstance><productId>66acd000-77fe-1000-9115-d8025841129e</productId><offerLicenseTypeId>14</offerLicenseTypeId><productInstanceId>17db4b59-7093-4006-801b-64bfc3e0bcb0</productInstanceId><isAcquirable>1</isAcquirable><isAdSupported>0</isAdSupported><packageSize>100216781</packageSize><installSize>6218</installSize><packageType>1</packageType><gameRegion>16776703</gameRegion><contentId>F9tLWXCTBhtkv8PgvLAAv/FOrLs=</contentId><licenseExtensionBits>1</licenseExtensionBits></productInstance></offerInstance><offerInstance><offerId>urn:uuid:00000001-0000-4000-8000-00005841129e</offerId><hexOfferId>0x5841129e00000001</hexOfferId><offerInstanceId>urn:uuid:a7cfdb10-ef3a-4042-999a-dfa4540f4bdc</offerInstanceId><startDate>2012-11-21T09:00:00Z</startDate><endDate>2799-12-31T00:00:00Z</endDate><paymentType>2</paymentType><price>400</price><pricetext></pricetext><taxType>0</taxType><tiers><tier>3</tier></tiers><stores><store>1</store></stores><productInstance><productId>66acd000-77fe-1000-9115-d8025841129e</productId><offerLicenseTypeId>14</offerLicenseTypeId><productInstanceId>17db4b59-7093-4006-801b-64bfc3e0bcb0</productInstanceId><isAcquirable>1</isAcquirable><isAdSupported>0</isAdSupported><packageSize>100216781</packageSize><installSize>6218</installSize><packageType>1</packageType><gameRegion>16776703</gameRegion><contentId>F9tLWXCTBhtkv8PgvLAAv/FOrLs=</contentId><licenseExtensionBits>1</licenseExtensionBits></productInstance></offerInstance><offerInstance><offerId>urn:uuid:00000001-0000-4000-8000-00005841129e</offerId><hexOfferId>0x5841129e00000001</hexOfferId><offerInstanceId>urn:uuid:9f9936f1-1334-476b-a695-e2ec0509064e</offerInstanceId><startDate>2012-11-21T09:00:00Z</startDate><endDate>2799-12-31T00:00:00Z</endDate><paymentType>2</paymentType><price>400</price><pricetext></pricetext><taxType>0</taxType><tiers><tier>2</tier></tiers><stores><store>1</store></stores><productInstance><productId>66acd000-77fe-1000-9115-d8025841129e</productId><offerLicenseTypeId>14</offerLicenseTypeId><productInstanceId>17db4b59-7093-4006-801b-64bfc3e0bcb0</productInstanceId><isAcquirable>1</isAcquirable><isAdSupported>0</isAdSupported><packageSize>100216781</packageSize><installSize>6218</installSize><packageType>1</packageType><gameRegion>16776703</gameRegion><contentId>F9tLWXCTBhtkv8PgvLAAv/FOrLs=</contentId><licenseExtensionBits>1</licenseExtensionBits></productInstance></offerInstance></offerInstances><offerTargetTypes><offerTargetType><mediaType>5</mediaType><avatarBodyType>0</avatarBodyType><tiers>2</tiers><stores>1</stores></offerTargetType><offerTargetType><mediaType>5</mediaType><avatarBodyType>0</avatarBodyType><tiers>3</tiers><stores>1</stores></offerTargetType><offerTargetType><mediaType>23</mediaType><avatarBodyType>0</avatarBodyType><tiers>2</tiers><stores>1</stores></offerTargetType><offerTargetType><mediaType>23</mediaType><avatarBodyType>0</avatarBodyType><tiers>3</tiers><stores>1</stores></offerTargetType></offerTargetTypes><productType>23</productType><reducedTitle>Sonic the Fighters</reducedTitle><reducedDescription>Join Sonic and friends in battle in this classic arcade game from AM2.  Originally on the console as part of the Sonic Gems collection, Sonic the Fighters is back with an all-new online mode, including both online versus and tournament play.   </reducedDescription><fullTitle>Full Game - Sonic the Fighters</fullTitle><fullDescription>Join Sonic and friends in battle in this classic arcade game from AM2.  Originally on consoles as part of the Sonic Gems collection, Sonic the Fighters is back with an all-new online mode, including both online versus and tournament play.    In single player mode, choose from 10 playable characters and fight through 8 stages to stop Dr. Robotnik and Metal Sonic from unleashing the Death Egg II!  Features include:  True to its arcade form with all-new online modes  All 8 original characters and arenas  Online versus mode for head-to-head matches  Online Room match mode for up to 6 players   </fullDescription><voiceDisplayTitle>Sonic the Fighters</voiceDisplayTitle><visibilityDate>2012-11-21T00:00:00</visibilityDate><globalOriginalReleaseDate>2012-11-28T00:00:00</globalOriginalReleaseDate><countryReleaseDate>2012-11-28T00:00:00</countryReleaseDate><ratingId>10</ratingId><ratingDescriptors><ratingDescriptor level="1.0000">41</ratingDescriptor></ratingDescriptors><ratingDisclaimers><ratingDisclaimer><ratingDisclaimerId>2</ratingDisclaimerId><ratingDisclaimerText>Online Interactions Not Rated by the ESRB</ratingDisclaimerText></ratingDisclaimer></ratingDisclaimers><developerName>SEGA</developerName><publisherName>SEGA</publisherName><titleId>1480659614</titleId><hexTitleId>0x5841129e</hexTitleId><effectiveTitleId>1480659614</effectiveTitleId><gameReducedTitle>Sonic the Fighters</gameReducedTitle><userRating>4.00</userRating><numberOfRatings>10747</numberOfRatings><gameCapabilities><offlinePlayersMin>2</offlinePlayersMin><offlinePlayersMax>2</offlinePlayersMax><offlineMaxHDTVModeId>3</offlineMaxHDTVModeId><offlinePeripheralArcadeStick>1</offlinePeripheralArcadeStick><offlineDolbyDigital>1</offlineDolbyDigital><onlineMultiplayerMin>2</onlineMultiplayerMin><onlineMultiplayerMax>6</onlineMultiplayerMax><onlineLeaderboards>1</onlineLeaderboards><onlineVoice>1</onlineVoice></gameCapabilities><images><image><imageMediaId>BE9AB071-3FEA-4AC5-A5C4-B7824A4A58C8</imageMediaId><imageMediaInstanceId>2FE9D9BE-AAA8-48B4-9B64-1409D34B63FD</imageMediaInstanceId><imageMediaType>14</imageMediaType><relationshipType>33</relationshipType><format>4</format><size>23</size><fileUrl>http://download.xbox.com/content/images/66acd000-77fe-1000-9115-d8025841129e/1033/boxartlg.jpg</fileUrl><parentGameMediaId>66ACD000-77FE-1000-9115-D8025841129E</parentGameMediaId></image><image><imageMediaId>9A2D33D5-F988-418B-9247-417008253C79</imageMediaId><imageMediaInstanceId>368F4F67-20CF-482F-A302-303F012C36F6</imageMediaInstanceId><imageMediaType>14</imageMediaType><relationshipType>33</relationshipType><format>4</format><size>30</size><fileUrl>http://download.xbox.com/content/images/66acd000-77fe-1000-9115-d8025841129e/1033/boxartsm.jpg</fileUrl><parentGameMediaId>66ACD000-77FE-1000-9115-D8025841129E</parentGameMediaId></image><image><imageMediaId>AE490849-5B73-4699-9D54-6997F733848A</imageMediaId><imageMediaInstanceId>299520AA-7BE8-415D-BDC9-3599E20EFD66</imageMediaInstanceId><imageMediaType>14</imageMediaType><relationshipType>25</relationshipType><format>4</format><size>22</size><fileUrl>http://download.xbox.com/content/images/66acd000-77fe-1000-9115-d8025841129e/1033/background.jpg</fileUrl><parentGameMediaId>66ACD000-77FE-1000-9115-D8025841129E</parentGameMediaId></image><image><imageMediaId>19B8AEEB-B1C8-494E-8EC8-CF83AD8A08EF</imageMediaId><imageMediaInstanceId>20552EE3-75AD-4C5E-B29C-5348B807E997</imageMediaInstanceId><imageMediaType>14</imageMediaType><relationshipType>27</relationshipType><format>5</format><size>15</size><fileUrl>http://download.xbox.com/content/images/66acd000-77fe-1000-9115-d8025841129e/1033/banner.png</fileUrl><parentGameMediaId>66ACD000-77FE-1000-9115-D8025841129E</parentGameMediaId></image><image><imageMediaId>944EDFC6-39BD-48E3-B01E-8FA73EEB0023</imageMediaId><imageMediaInstanceId>021CA551-9744-4A5B-AA8D-F8818CB86BB4</imageMediaInstanceId><imageMediaType>14</imageMediaType><relationshipType>23</relationshipType><format>5</format><size>14</size><fileUrl>http://download.xbox.com/content/images/66acd000-77fe-1000-9115-d8025841129e/1033/tile.png</fileUrl><parentGameMediaId>66ACD000-77FE-1000-9115-D8025841129E</parentGameMediaId></image></images><slideShows><slideShow><image><displayOrder>1</displayOrder><imageMediaId>7E155406-7284-40C3-8218-CA46019F3576</imageMediaId><imageMediaInstanceId>76A6EBBA-E81F-4BA1-9046-7ED6CEE586DB</imageMediaInstanceId><imageMediaType>14</imageMediaType><relationshipType>32</relationshipType><format>4</format><size>27</size><fileUrl>http://download.xbox.com/content/images/66acd000-77fe-1000-9115-d8025841129e/1033/screenlg1.jpg</fileUrl></image><image><displayOrder>2</displayOrder><imageMediaId>7664A4F3-67BE-4960-80FA-6C7EA2C13BF8</imageMediaId><imageMediaInstanceId>4CE34414-335E-4E8E-9E64-0302AF6FA913</imageMediaInstanceId><imageMediaType>14</imageMediaType><relationshipType>32</relationshipType><format>4</format><size>27</size><fileUrl>http://download.xbox.com/content/images/66acd000-77fe-1000-9115-d8025841129e/1033/screenlg2.jpg</fileUrl></image><image><displayOrder>3</displayOrder><imageMediaId>D8FAB383-DB38-497C-9C0A-5C9DB3EA37CF</imageMediaId><imageMediaInstanceId>0395254F-A4E4-4D1E-A295-6D296F6B5E46</imageMediaInstanceId><imageMediaType>14</imageMediaType><relationshipType>32</relationshipType><format>4</format><size>27</size><fileUrl>http://download.xbox.com/content/images/66acd000-77fe-1000-9115-d8025841129e/1033/screenlg3.jpg</fileUrl></image><image><displayOrder>4</displayOrder><imageMediaId>A5CF4573-B2DF-4DBC-9526-9628797B9A59</imageMediaId><imageMediaInstanceId>5415B362-C794-47F8-A890-7187BA72EFD2</imageMediaInstanceId><imageMediaType>14</imageMediaType><relationshipType>32</relationshipType><format>4</format><size>27</size><fileUrl>http://download.xbox.com/content/images/66acd000-77fe-1000-9115-d8025841129e/1033/screenlg4.jpg</fileUrl></image><image><displayOrder>5</displayOrder><imageMediaId>42964A28-181C-47D3-8BE6-675E21D63FE0</imageMediaId><imageMediaInstanceId>62D221E4-E5CF-4354-87EF-4CB010BFD6BD</imageMediaInstanceId><imageMediaType>14</imageMediaType><relationshipType>32</relationshipType><format>4</format><size>27</size><fileUrl>http://download.xbox.com/content/images/66acd000-77fe-1000-9115-d8025841129e/1033/screenlg5.jpg</fileUrl></image><image><displayOrder>6</displayOrder><imageMediaId>140714A4-1467-46C7-AC66-B0405804EA1D</imageMediaId><imageMediaInstanceId>ADCE295E-3979-4E6B-8D04-6E850F486026</imageMediaInstanceId><imageMediaType>14</imageMediaType><relationshipType>32</relationshipType><format>4</format><size>27</size><fileUrl>http://download.xbox.com/content/images/66acd000-77fe-1000-9115-d8025841129e/1033/screenlg6.jpg</fileUrl></image></slideShow></slideShows><parentProducts><parentProduct><parentProductId>66acd000-77fe-1000-9115-d8025841129e</parentProductId><parentReducedTitle>Sonic the Fighters</parentReducedTitle><parentSortOrder>0</parentSortOrder></parentProduct></parentProducts><categories><category><categoryId>3000</categoryId><categoryName>Game Genres</categoryName><categorySystemId>3000</categorySystemId></category><category><categoryId>3006</categoryId><categoryName>Fighting</categoryName><categorySystemId>3000</categorySystemId><parentCategoryId>3027</parentCategoryId></category><category><categoryId>3027</categoryId><categoryName>Xbox LIVE Games</categoryName><categorySystemId>3000</categorySystemId><parentCategoryId>3000</parentCategoryId></category><category><categoryId>12001</categoryId><categoryName>Game Publisher Bit 1</categoryName><categorySystemId>12000</categorySystemId></category></categories></a:entry></a:feed>